[
  {
    "title": "ゲゲゲの鬼太郎 激突!!異次元妖怪の大反乱",
    "titleTranslate": {
      "zh-Hans": [
        "鬼太郎 冲突!!异次元妖怪的大叛乱"
      ]
    },
    "type": "movie",
    "lang": "ja",
    "officialSite": "",
    "begin": "1986-12-20T16:00:00.000Z",
    "end": "1986-12-20T17:00:00.000Z",
    "sites": [
      {
        "site": "bangumi",
        "id": "211096"
      },
      {
        "site": "iqiyi",
        "id": "a_19rrhb4kld",
        "begin": "2015-08-11T08:03:32.000Z"
      },
      {
        "site": "unext",
        "id": "SID0003300",
        "begin": "2015-02-16T15:00:00.000Z",
        "broadcast": "R/2015-02-16T15:00:00.000Z/P7D"
      },
      {
        "site": "danime",
        "id": "24690",
        "begin": "2022-06-15T01:00:00.000Z",
        "broadcast": "R/2022-06-15T01:00:00.000Z/P7D"
      }
    ],
    "animeSeason": {
      "season": "FALL",
      "year": 1986,
      "month": "12"
    },
    "status": "FINISHED",
    "episodes": 1,
    "picture": "https://cdn.myanimelist.net/images/anime/1383/100504.jpg",
    "thumbnail": "https://cdn.myanimelist.net/images/anime/1383/100504t.jpg",
    "synonyms": [
      "GeGeGe no Kitarou: Gekitotsu!! Ijigen Youkai no Daihanran",
      "Gegege no Kitaro: Gekitotsu!! Ijigen Yokai no Daihanran",
      "Gegege no Kitarou: Crash!! The Great Rising of Demons from Another Dimension",
      "Gegege no Kitarō: Gekitotsu!! Ijigen Yōkai no Daihanran",
      "Spooky Kitaro: Crash!! The Great Rebellion of the Multi-Dimensional Youkai",
      "Spooky Kitaro: Crash!! The Great Rebellion of the Multi-Dimensional Yōkai",
      "ゲゲゲの鬼太郎 激突!!異次元妖怪の大反乱",
      "ゲゲゲの鬼太郎 激突！！異次元妖怪の大反乱"
    ]
  },
  {
    "title": "ドラゴンボール 神龍の伝説",
    "titleTranslate": {
      "zh-Hans": [
        "龙珠 神龙传说"
      ]
    },
    "type": "movie",
    "lang": "ja",
    "officialSite": "",
    "begin": "1986-12-20T16:00:00.000Z",
    "end": "1986-12-20T16:30:00.000Z",
    "sites": [
      {
        "site": "bangumi",
        "id": "44936"
      },
      {
        "site": "nicovideo",
        "id": "DB_shenron",
        "begin": ""
      },
      {
        "site": "iqiyi",
        "id": "a_19rrhb4015",
        "begin": "2016-02-04T10:34:13.000Z"
      },
      {
        "site": "unext",
        "id": "SID0010759",
        "begin": "2018-07-27T03:00:00.000Z",
        "broadcast": "R/2018-07-27T03:00:00.000Z/P7D"
      },
      {
        "site": "abema",
        "id": "184-155",
        "begin": "",
        "broadcast": ""
      }
    ],
    "animeSeason": {
      "season": "FALL",
      "year": 1986,
      "month": "12"
    },
    "status": "FINISHED",
    "episodes": 1,
    "picture": "https://cdn.myanimelist.net/images/anime/1992/121522.jpg",
    "thumbnail": "https://cdn.myanimelist.net/images/anime/1992/121522t.jpg",
    "synonyms": [
      "A lenda de Sheron o dragón",
      "Bola de Drac: La Llegenda del Drac Xeron",
      "DB Movie 1",
      "DBMV1",
      "DRAGON BALL 神龍の伝説",
      "Dragon Ball - A Lenda de Shenron",
      "Dragon Ball - La leggenda del drago Shenron",
      "Dragon Ball - La leggenda delle sette sfere",
      "Dragon Ball 1 - La légende de Shenron",
      "Dragon Ball Movie 1",
      "Dragon Ball Movie 1 - Legenda Shenlonga",
      "Dragon Ball Movie 1: Curse of the Blood Rubies",
      "Dragon Ball der Film: Die Legende von Shenlong",
      "Dragon Ball la Película: La Leyenda de Shenron",
      "Dragon Ball le Film: La Légende De Shenron",
      "Dragon Ball 神龍の伝説",
      "Dragon Ball: Curse of the Blood Rubies",
      "Dragon Ball: Die Legende von Shenlong",
      "Dragon Ball: La Leyenda Del Dragón Xeron",
      "Dragon Ball: La Leyenda de Shenron",
      "Dragon Ball: La Leyenda del Dragón Shenron",
      "Dragon Ball: La Légende de Shéron",
      "Dragon Ball: La leggenda del drago Shenron",
      "Dragon Ball: La leggenda delle sette sfere",
      "Dragon Ball: Shen Long no Densetsu",
      "Dragon Ball: The Legend of Shenlong",
      "Dragon Ball: The Legend of Shenron",
      "Dragonball - The Movie 1: Die Legende von Shenlong",
      "Dragonball Movie 1",
      "Dragonball: Die Legende von Shen Long",
      "Dragonball: Die Legende von Shenlong",
      "La leggenda di Dragon Ball",
      "Shenron no Densetsu",
      "The Legend of Shenlong",
      "مغامرات كوجو",
      "ดราก้อนบอล มูฟวี่ 1 ตอน ตำนานเทพมังกร",
      "ドラゴンボール 神龍の伝説",
      "龍珠: 神龍傳說",
      "龙珠 神龙传说",
      "龙珠：神龙传说"
    ]
  },
  {
    "title": "タッチ2 さよならの贈り物",
    "titleTranslate": {
      "zh-Hans": [
        "棒球英豪2 再见的礼物",
        "棒球英豪 剧场版",
        "邻家女孩剧场版 再见的礼物"
      ],
      "en": [
        "Touch 2: The Farewell Gift"
      ]
    },
    "type": "movie",
    "lang": "ja",
    "officialSite": "",
    "begin": "1986-12-12T16:00:00.000Z",
    "end": "1986-12-12T16:00:00.000Z",
    "sites": [
      {
        "site": "bangumi",
        "id": "18046"
      },
      {
        "site": "bilibili",
        "id": "2426",
        "begin": "2013-02-25T15:50:34.000Z",
        "broadcast": "R/2013-02-25T15:50:34.000Z/P7D"
      }
    ],
    "animeSeason": {
      "season": "FALL",
      "year": 1986,
      "month": "12"
    },
    "status": "FINISHED",
    "episodes": 1,
    "picture": "https://cdn.myanimelist.net/images/anime/8/3046.jpg",
    "thumbnail": "https://cdn.myanimelist.net/images/anime/8/3046t.jpg",
    "synonyms": [
      "Farewell Gift",
      "Théo ou la Batte de la Victoire : Le Cadeau d’Adieu",
      "Théo ou la batte de la victoire - Le cadeau d`adieu",
      "Touch 2",
      "Touch 2, Farewell Gift",
      "Touch 2: Farewell Gift",
      "Touch 2: The Farewell Gift",
      "Touch Bateadores: El Legado de Kazuya",
      "Touch Movie 2: Sayonara no Okurimono",
      "Touch, Bateadores: El legado de Kazuya",
      "Touch: Théo ou La Batte de La Victoire: Le Cadeau d'Adieu",
      "touch movie 2",
      "タッチ2 さよならの贈り物",
      "棒球英豪2 再见的礼物"
    ]
  },
  {
    "title": "時空の旅人",
    "titleTranslate": {
      "zh-Hans": [
        "时空的旅人",
        "时空旅人"
      ]
    },
    "type": "movie",
    "lang": "ja",
    "officialSite": "http://www.madhouse.co.jp/works/1986-1983/works_movie_timestranger.html",
    "begin": "1986-12-19T16:00:00.000Z",
    "broadcast": "",
    "end": "1986-12-19T17:31:00.000Z",
    "comment": "",
    "sites": [
      {
        "site": "bangumi",
        "id": "52782"
      },
      {
        "site": "unext",
        "id": "SID0042776",
        "begin": "2019-12-08T03:00:00.000Z",
        "broadcast": "R/2019-12-08T03:00:00.000Z/P7D"
      },
      {
        "site": "danime",
        "id": "10061",
        "begin": "2012-06-26T15:00:00.000Z",
        "broadcast": "R/2012-06-26T15:00:00.000Z/P7D"
      }
    ],
    "animeSeason": {
      "season": "FALL",
      "year": 1986,
      "month": "12"
    },
    "status": "FINISHED",
    "episodes": 1,
    "picture": "https://cdn.myanimelist.net/images/anime/10/4740.jpg",
    "thumbnail": "https://cdn.myanimelist.net/images/anime/10/4740t.jpg",
    "synonyms": [
      "Keliautojas laiku",
      "时空的旅人",
      "時空[とき]の旅人 Time Stranger",
      "時空の旅人",
      "時空の旅人 -Time Stranger-"
    ]
  },
  {
    "title": "Mr.ペンペンII",
    "titleTranslate": {},
    "type": "tv",
    "lang": "ja",
    "officialSite": "",
    "begin": "1986-12-28T16:00:00.000Z",
    "broadcast": "",
    "end": "1986-12-28T16:00:00.000Z",
    "comment": "",
    "sites": [
      {
        "site": "bangumi",
        "id": "313670"
      },
      {
        "site": "unext",
        "id": "SID0012549",
        "begin": "2016-02-18T15:00:00.000Z",
        "broadcast": "R/2016-02-18T15:00:00.000Z/P7D"
      },
      {
        "site": "danime",
        "id": "23317",
        "begin": "2020-03-06T01:00:00.000Z",
        "broadcast": "R/2020-03-06T01:00:00.000Z/P7D"
      }
    ],
    "animeSeason": {
      "season": "FALL",
      "year": 1986,
      "month": "12"
    },
    "status": "FINISHED",
    "episodes": 1,
    "picture": "https://cdn.myanimelist.net/images/anime/13/47025.jpg",
    "thumbnail": "https://cdn.myanimelist.net/images/anime/13/47025t.jpg",
    "synonyms": [
      "Mr. Pen Pen 2",
      "Mr.ペンペンII"
    ]
  },
  {
    "title": "キン肉マン 正義超人vs戦士超人",
    "titleTranslate": {
      "zh-Hans": [
        "筋肉人 正义超人vs战士超人"
      ]
    },
    "type": "movie",
    "lang": "ja",
    "officialSite": "",
    "begin": "1986-12-19T16:00:00.000Z",
    "broadcast": "",
    "end": "1986-12-19T16:00:00.000Z",
    "comment": "",
    "sites": [
      {
        "site": "bangumi",
        "id": "215106"
      },
      {
        "site": "unext",
        "id": "SID0003118",
        "begin": "2015-02-16T15:00:00.000Z",
        "broadcast": "R/2015-02-16T15:00:00.000Z/P7D"
      },
      {
        "site": "danime",
        "id": "20320",
        "begin": "2020-02-01T01:00:00.000Z",
        "broadcast": "R/2020-02-01T01:00:00.000Z/P7D"
      }
    ],
    "animeSeason": {
      "season": "FALL",
      "year": 1986,
      "month": "12"
    },
    "status": "FINISHED",
    "episodes": 1,
    "picture": "https://cdn.myanimelist.net/images/anime/1102/97585.jpg",
    "thumbnail": "https://cdn.myanimelist.net/images/anime/1102/97585t.jpg",
    "synonyms": [
      "Justice Supermen vs. Fighter Supermen",
      "Kinnikuman Movie 7: Seigi Choujin vs Senshi Choujin",
      "Kinnikuman: Justice Superman vs. Soldier Superman",
      "Kinnikuman: Seigi Choujin vs Senshi Choujin",
      "Kinnikuman: Seigi Chōjin vs Senshi Chōjin",
      "キン肉マン 正義超人VS戦士超人",
      "キン肉マン 正義超人vs戦士超人",
      "キン肉マン 正義超人ＶＳ戦士超人"
    ]
  }
]