[
  {
    "title": "ゲッターロボG",
    "titleTranslate": {
      "zh-Hans": [
        "盖塔机器人G"
      ]
    },
    "type": "tv",
    "lang": "ja",
    "officialSite": "",
    "begin": "1975-05-14T15:00:00.000Z",
    "broadcast": "R/1975-05-14T15:00:00.000Z/P7D",
    "end": "1976-03-24T16:00:00.000Z",
    "comment": "",
    "sites": [
      {
        "site": "bangumi",
        "id": "25921"
      },
      {
        "site": "danime",
        "id": "24818",
        "begin": "2023-02-28T01:00:00.000Z",
        "broadcast": "R/2023-02-28T01:00:00.000Z/P7D"
      }
    ],
    "animeSeason": {
      "season": "SPRING",
      "year": 1975,
      "month": "05"
    },
    "status": "FINISHED",
    "episodes": 39,
    "picture": "https://cdn.myanimelist.net/images/anime/8/58399.jpg",
    "thumbnail": "https://cdn.myanimelist.net/images/anime/8/58399t.jpg",
    "synonyms": [
      "Force Five: Starvengers",
      "Formators",
      "Getta Robo G",
      "Getta Robot G",
      "Getter Robo: Getter Robo G",
      "Getter Robot G",
      "Jet Robot",
      "Robo Formers",
      "Starvengers",
      "The Formators",
      "ゲッターロボG",
      "게타로보"
    ]
  }
]