{
  "title": "ポケットモンスター ジ・オリジン",
  "titleTranslate": {
    "zh-Hans": [
      "精灵宝可梦 起源"
    ]
  },
  "type": "tv",
  "lang": "ja",
  "officialSite": "http://www.pokemon.co.jp/ex/origin/",
  "begin": "2013-10-02T16:00:00.000Z",
  "end": "2013-10-02T18:00:00.000Z",
  "sites": [
    {
      "site": "letv",
      "id": "93668",
      "begin": ""
    },
    {
      "site": "bangumi",
      "id": "81372"
    },
    {
      "site": "youku",
      "id": "523f77d60a2211e3b8b7",
      "begin": "2013-10-05T08:19:39.000Z"
    },
    {
      "site": "bilibili",
      "id": "4378",
      "begin": "2013-10-01T16:00:00.000Z",
      "broadcast": "R/2016-06-03T03:27:00.000Z/P7D"
    },
    {
      "site": "anidb",
      "id": "230"
    },
    {
      "site": "anilist",
      "id": "527"
    },
    {
      "site": "anime-planet",
      "id": "pokemon-generations"
    },
    {
      "site": "anisearch",
      "id": "3139"
    },
    {
      "site": "kitsu",
      "id": "486"
    },
    {
      "site": "livechart",
      "id": "3702"
    },
    {
      "site": "livechart",
      "id": "3816"
    },
    {
      "site": "livechart",
      "id": "3979"
    },
    {
      "site": "livechart",
      "id": "3992"
    },
    {
      "site": "livechart",
      "id": "4045"
    },
    {
      "site": "livechart",
      "id": "4466"
    },
    {
      "site": "livechart",
      "id": "4505"
    },
    {
      "site": "livechart",
      "id": "5008"
    },
    {
      "site": "livechart",
      "id": "5217"
    },
    {
      "site": "livechart",
      "id": "5345"
    },
    {
      "site": "livechart",
      "id": "5371"
    },
    {
      "site": "livechart",
      "id": "5627"
    },
    {
      "site": "livechart",
      "id": "5641"
    },
    {
      "site": "livechart",
      "id": "5643"
    },
    {
      "site": "livechart",
      "id": "8945"
    },
    {
      "site": "myanimelist",
      "id": "527"
    },
    {
      "site": "notify",
      "id": "sv1ocKimg"
    }
  ],
  "animeSeason": {
    "season": "FALL",
    "year": 2013,
    "month": "10"
  },
  "status": "FINISHED",
  "episodes": 4,
  "picture": "https://cdn.myanimelist.net/images/anime/7/53701.jpg",
  "thumbnail": "https://cdn.myanimelist.net/images/anime/7/53701t.jpg",
  "synonyms": [
    "Pocket Monsters Origins",
    "Pocket Monsters: THE ORIGIN",
    "Pocket Monsters: The Origin",
    "Pokemon Origins",
    "Pokemon: Origins",
    "Pokèmon: Le origini",
    "Pokémon : Les Origines",
    "Pokémon : les origines",
    "Pokémon Le origini",
    "Pokémon Origins",
    "Pokémon: Los Orígenes",
    "Pokémon: Origins",
    "Pokémon: The Origin",
    "Pokémon: los orígenes",
    "pm special 4",
    "Покемоны: Начало",
    "ポケットモンスター THE ORIGIN",
    "ポケットモンスター ジ・オリジン"
  ]
}