[
  {
    "title": "かみさまみならい ヒミツのここたま",
    "titleTranslate": {
      "zh-Hans": [
        "见习神仙 秘密的心灵",
        "见习神明 秘密的心灵 第一部",
        "见习神仙 秘密的cocotama"
      ],
      "zh-Hant": [
        "見習神仙精靈"
      ],
      "en": [
        "Kamisama Minarai - Himitsu no Cocotama"
      ]
    },
    "type": "tv",
    "lang": "ja",
    "officialSite": "http://coco-tama.com/",
    "begin": "2015-10-01T09:00:00.000Z",
    "end": "2017-03-30T09:25:00.000Z",
    "sites": [
      {
        "site": "bangumi",
        "id": "137894"
      },
      {
        "site": "nicovideo",
        "id": "cocotama",
        "begin": "2015-10-08T03:00:00.000Z",
        "broadcast": "R/2015-10-08T03:00:00.000Z/P7D"
      },
      {
        "site": "bangumi_moe",
        "id": "560d0d629286e15329cf94dc"
      },
      {
        "site": "mikan",
        "id": "575"
      }
    ],
    "animeSeason": {
      "season": "FALL",
      "year": 2015,
      "month": "10"
    },
    "status": "FINISHED",
    "episodes": 139,
    "picture": "https://cdn.myanimelist.net/images/anime/4/84883.jpg",
    "thumbnail": "https://cdn.myanimelist.net/images/anime/4/84883t.jpg",
    "synonyms": [
      "God Apprentices: Secretive Cocotama",
      "Kamisama Minarai: Cocotama-dou",
      "Kamisama Minarai: Himitsu no Kokotama",
      "かみさま みならいここたま道",
      "かみさまみならい ここたま道",
      "かみさまみならい ヒミツのここたま",
      "かみさまみならいひみつのここたま",
      "见习神仙 秘密的心灵"
    ]
  },
  {
    "title": "ランス・アンド・マスクス",
    "titleTranslate": {
      "zh-Hans": [
        "枪与假面舞会",
        "枪的假面舞会"
      ],
      "en": [
        "Lance N' Masques"
      ]
    },
    "type": "tv",
    "lang": "ja",
    "officialSite": "http://www.tbs.co.jp/anime/lance/",
    "begin": "2015-10-01T16:46:00.000Z",
    "end": "2015-12-17T17:21:00.000Z",
    "sites": [
      {
        "site": "bilibili",
        "id": "2719",
        "begin": "2015-10-02T04:00:00.000Z",
        "broadcast": "R/2015-10-02T04:00:00.000Z/P7D"
      },
      {
        "site": "youku",
        "id": "1f9945d2d29f11e38b3f",
        "begin": "2015-10-02T04:00:00.000Z"
      },
      {
        "site": "iqiyi",
        "id": "a_19rrhbb445",
        "begin": "2015-10-02T04:00:00.000Z"
      },
      {
        "site": "bangumi",
        "id": "103023"
      },
      {
        "site": "nicovideo",
        "id": "lance",
        "begin": "2015-10-08T13:30:00.000Z",
        "broadcast": "R/2015-10-08T13:30:00.000Z/P7D"
      },
      {
        "site": "unext",
        "id": "SID0020280",
        "begin": "2023-09-22T03:00:00.000Z",
        "broadcast": "R/2023-09-22T03:00:00.000Z/P7D"
      },
      {
        "site": "dmhy",
        "id": "Masques"
      },
      {
        "site": "bangumi_moe",
        "id": "560d0d999286e15329cf94e0"
      },
      {
        "site": "mikan",
        "id": "577"
      }
    ],
    "animeSeason": {
      "season": "FALL",
      "year": 2015,
      "month": "10"
    },
    "status": "FINISHED",
    "episodes": 12,
    "picture": "https://cdn.myanimelist.net/images/anime/13/76576.jpg",
    "thumbnail": "https://cdn.myanimelist.net/images/anime/13/76576t.jpg",
    "synonyms": [
      "LN'M",
      "LN’M",
      "Lance N'Masques",
      "Lance N` Masques",
      "Lance N’ Masques",
      "Lance and Masks",
      "Lance and Masques",
      "らんすあんどますくす",
      "ランス・アンド・マスクス",
      "枪与假面舞会"
    ]
  },
  {
    "title": "ヘヴィーオブジェクト",
    "titleTranslate": {
      "zh-Hans": [
        "重装武器"
      ],
      "en": [
        "Heavy Object",
        "HEAVY OBJECT"
      ],
      "zh-Hant": [
        "重裝武器"
      ]
    },
    "type": "tv",
    "lang": "ja",
    "officialSite": "http://heavyobject.net/",
    "begin": "2015-10-02T15:30:00.000Z",
    "end": "2016-03-25T16:00:00.000Z",
    "sites": [
      {
        "site": "bilibili",
        "id": "2740",
        "begin": "2015-10-02T19:00:00.000Z",
        "broadcast": "R/2015-10-02T19:00:00.000Z/P7D"
      },
      {
        "site": "bangumi",
        "id": "115008"
      },
      {
        "site": "nicovideo",
        "id": "heavyobject",
        "begin": "2015-10-05T03:00:00.000Z",
        "broadcast": "R/2015-10-05T03:00:00.000Z/P7D"
      },
      {
        "site": "qq",
        "id": "8/8nurpd3uitw4dei",
        "begin": ""
      },
      {
        "site": "iqiyi",
        "id": "a_xs7i0gj315",
        "begin": ""
      },
      {
        "site": "muse_hk",
        "id": "PLuxqoToY7UcjbWmWnY8cCDlqeJ-L62j1i",
        "begin": "2023-01-18T16:00:00.000Z",
        "broadcast": "R/2023-01-18T16:00:00.000Z/P1D"
      },
      {
        "site": "gamer",
        "id": "73148",
        "begin": "2015-12-13T16:00:00.000Z",
        "broadcast": "R/2015-12-13T16:00:00.000Z/P7D"
      },
      {
        "site": "unext",
        "id": "SID0020278",
        "begin": "2019-11-29T03:00:00.000Z",
        "broadcast": "R/2019-11-29T03:00:00.000Z/P7D"
      },
      {
        "site": "dmhy",
        "id": "裝武|Heavy"
      },
      {
        "site": "bangumi_moe",
        "id": "560d0ec79286e15329cf94ec"
      },
      {
        "site": "mikan",
        "id": "582"
      },
      {
        "site": "gamer_hk",
        "id": "73148",
        "begin": "2015-12-13T16:00:00.000Z",
        "broadcast": "R/2015-12-13T16:00:00.000Z/P7D"
      }
    ],
    "animeSeason": {
      "season": "FALL",
      "year": 2015,
      "month": "10"
    },
    "status": "FINISHED",
    "episodes": 24,
    "picture": "https://cdn.myanimelist.net/images/anime/13/75940.jpg",
    "thumbnail": "https://cdn.myanimelist.net/images/anime/13/75940t.jpg",
    "synonyms": [
      "Тяжёлый объект",
      "ยุทธการอาวุธมหาประลัย",
      "へびーおぶじぇくと",
      "ヘヴィーオブジェクト",
      "重装武器",
      "헤비 오브젝트"
    ]
  },
  {
    "title": "ルパン三世(2015)",
    "titleTranslate": {
      "zh-Hans": [
        "鲁邦三世 新系列",
        "鲁邦三世",
        "鲁邦三世 第四期",
        "鲁邦三世 2015"
      ],
      "en": [
        "Lupin Sansei 2015",
        "LUPIN THE THIRD"
      ],
      "zh-Hant": [
        "魯邦三世",
        "魯邦三世Part4",
        "魯邦三世 PART4"
      ]
    },
    "type": "tv",
    "lang": "ja",
    "officialSite": "http://lupin-new-season.jp/",
    "begin": "2015-10-01T17:50:00.000Z",
    "end": "2016-03-17T17:34:00.000Z",
    "sites": [
      {
        "site": "bangumi",
        "id": "115661"
      },
      {
        "site": "nicovideo",
        "id": "lupin-new-season",
        "begin": "2016-01-13T15:00:00.000Z",
        "broadcast": ""
      },
      {
        "site": "qq",
        "id": "m/mzc00200qe4kro7",
        "begin": ""
      },
      {
        "site": "muse_hk",
        "id": "PLuxqoToY7UchX3ZhQcPolG1Ho73Zcq6B-",
        "begin": "2021-11-11T16:00:00.000Z",
        "broadcast": "R/2021-11-11T16:00:00.000Z/P7D"
      },
      {
        "site": "gamer",
        "id": "73324",
        "begin": "2020-07-03T03:30:00.000Z",
        "broadcast": "R/2020-07-03T03:30:00.000Z/P7D"
      },
      {
        "site": "unext",
        "id": "SID0020989",
        "begin": "2018-04-05T03:00:00.000Z",
        "broadcast": "R/2018-04-05T03:00:00.000Z/P7D"
      },
      {
        "site": "dmhy",
        "id": "魯+新系|2015"
      },
      {
        "site": "bangumi_moe",
        "id": "5685725324f3d8c309bd4693"
      },
      {
        "site": "mikan",
        "id": "576"
      },
      {
        "site": "gamer_hk",
        "id": "73324",
        "begin": "2020-07-03T03:30:00.000Z",
        "broadcast": "R/2020-07-03T03:30:00.000Z/P7D"
      }
    ],
    "animeSeason": {
      "season": "FALL",
      "year": 1971,
      "month": "10"
    },
    "status": "FINISHED",
    "episodes": 23,
    "picture": "https://cdn.myanimelist.net/images/anime/10/15625.jpg",
    "thumbnail": "https://cdn.myanimelist.net/images/anime/10/15625t.jpg",
    "synonyms": [
      "Cliff Hanger",
      "Cliffhanger",
      "Edgar de la Cambriole",
      "Edgar de la cambriole - Saison 1",
      "Giacca verde",
      "Green Jacket",
      "Green jacket",
      "L3",
      "Le avventure di Lupin III",
      "Lupin III - Prima serie",
      "Lupin III Part 1",
      "Lupin III Part I",
      "Lupin III TV",
      "Lupin III.: Part 1",
      "Lupin III: Part 1",
      "Lupin III: Part I",
      "Lupin Sansei",
      "Lupin Sansei: Part I",
      "Lupin The Third: Part 1",
      "Lupin the 3rd",
      "Lupin the 3rd: Part 1",
      "Lupin the 3rd: Series 1",
      "Lupin the 3rd: The First TV Series",
      "Lupin the Third",
      "Lupin the Third Part 1",
      "Lupin the Third Part I",
      "Lupin the Third TV",
      "Rupan Sansei",
      "lupin1",
      "lupins1",
      "Люпен Трети",
      "לופין השלישי",
      "لوبن الثالث",
      "لوپین سوم",
      "るぱんさんせい",
      "ルパン三世",
      "ルパン三世 PART1",
      "ルパン三世(2015)",
      "鲁邦三世 (TV第1部)"
    ]
  },
  {
    "title": "ヤング ブラック・ジャック",
    "titleTranslate": {
      "zh-Hans": [
        "青年黑杰克",
        "少年怪医黑杰克"
      ],
      "en": [
        "Young Black Jack"
      ]
    },
    "type": "tv",
    "lang": "ja",
    "officialSite": "http://www.tbs.co.jp/anime/ybj/",
    "begin": "2015-10-01T17:16:00.000Z",
    "end": "2015-12-17T17:51:00.000Z",
    "sites": [
      {
        "site": "bilibili",
        "id": "2720",
        "begin": "2015-10-02T07:24:00.000Z",
        "broadcast": "R/2015-10-02T07:24:00.000Z/P7D"
      },
      {
        "site": "bangumi",
        "id": "133192"
      },
      {
        "site": "unext",
        "id": "SID0019858",
        "begin": "2015-10-02T06:00:00.000Z",
        "broadcast": "R/2015-10-02T06:00:00.000Z/P7D"
      },
      {
        "site": "dmhy",
        "id": "青年+黑"
      },
      {
        "site": "bangumi_moe",
        "id": "560d0da59286e15329cf94e2"
      },
      {
        "site": "mikan",
        "id": "578"
      }
    ],
    "animeSeason": {
      "season": "FALL",
      "year": 2015,
      "month": "10"
    },
    "status": "FINISHED",
    "episodes": 12,
    "picture": "https://cdn.myanimelist.net/images/anime/3/76125.jpg",
    "thumbnail": "https://cdn.myanimelist.net/images/anime/3/76125t.jpg",
    "synonyms": [
      "YBJ",
      "bj (2015)",
      "やんぐぶらっくじゃっく",
      "ヤング ブラックジャック",
      "ヤング ブラック・ジャック",
      "青年黑杰克"
    ]
  },
  {
    "title": "影鰐-KAGEWANI-",
    "titleTranslate": {
      "zh-Hans": [
        "影鳄"
      ],
      "en": [
        "Kagewani",
        "KAGEWANI"
      ]
    },
    "type": "tv",
    "lang": "ja",
    "officialSite": "http://kagewani.com/",
    "begin": "2015-10-02T14:17:00.000Z",
    "end": "2015-12-25T14:30:00.000Z",
    "sites": [
      {
        "site": "youku",
        "id": "02007bfe55ec11e5b2ad",
        "begin": "2015-10-14T07:05:10.000Z"
      },
      {
        "site": "bangumi",
        "id": "145735"
      },
      {
        "site": "nicovideo",
        "id": "kagewani",
        "begin": "2015-10-02T14:30:00.000Z",
        "broadcast": "R/2015-10-02T14:30:00.000Z/P7D"
      },
      {
        "site": "bilibili",
        "id": "2848",
        "begin": "2015-10-01T16:00:00.000Z",
        "broadcast": "R/2015-10-16T14:10:00.000Z/P7D"
      },
      {
        "site": "dmhy",
        "id": "影鱷|KAGEWANI"
      },
      {
        "site": "bangumi_moe",
        "id": "560d0e959286e15329cf94ea"
      },
      {
        "site": "mikan",
        "id": "579"
      }
    ],
    "animeSeason": {
      "season": "FALL",
      "year": 2015,
      "month": "10"
    },
    "status": "FINISHED",
    "episodes": 13,
    "picture": "https://cdn.myanimelist.net/images/anime/9/76060.jpg",
    "thumbnail": "https://cdn.myanimelist.net/images/anime/9/76060t.jpg",
    "synonyms": [
      "KAGEWANI",
      "かげわに",
      "影鰐",
      "影鰐 -KAGEWANI-",
      "影鰐-KAGEWANI-",
      "影鳄"
    ]
  },
  {
    "title": "ミス・モノクローム -The Animation- 3",
    "titleTranslate": {
      "zh-Hans": [
        "黑白小姐 第三季"
      ],
      "en": [
        "Miss Monochrome -The Animation- 3"
      ]
    },
    "type": "tv",
    "lang": "ja",
    "officialSite": "http://www.starchild.co.jp/special/miss_monochrome_anime_2/",
    "begin": "2015-10-02T13:30:00.000Z",
    "end": "2015-12-25T13:40:00.000Z",
    "sites": [
      {
        "site": "bilibili",
        "id": "2791",
        "begin": "2015-10-02T13:16:00.000Z",
        "broadcast": "R/2015-10-05T13:16:32.000Z/P7D"
      },
      {
        "site": "bangumi",
        "id": "145775"
      },
      {
        "site": "nicovideo",
        "id": "miss-monochrome3",
        "begin": "2015-10-04T16:30:00.000Z",
        "broadcast": "R/2015-10-04T16:30:00.000Z/P7D"
      },
      {
        "site": "unext",
        "id": "SID0020083",
        "begin": "2019-10-10T03:00:00.000Z",
        "broadcast": "R/2019-10-10T03:00:00.000Z/P7D"
      },
      {
        "site": "dmhy",
        "id": "Monochrome"
      },
      {
        "site": "bangumi_moe",
        "id": "560d0e6f9286e15329cf94e8"
      },
      {
        "site": "mikan",
        "id": "581"
      }
    ],
    "animeSeason": {
      "season": "FALL",
      "year": 2015,
      "month": "10"
    },
    "status": "FINISHED",
    "episodes": 13,
    "picture": "https://cdn.myanimelist.net/images/anime/6/76089.jpg",
    "thumbnail": "https://cdn.myanimelist.net/images/anime/6/76089t.jpg",
    "synonyms": [
      "Miss Monochrome - The Animation - 3",
      "Miss Monochrome - The Animation 3",
      "Miss Monochrome 3",
      "Miss Monochrome : The Animation 3",
      "Miss Monochrome Third Season",
      "Miss Monochrome: The Animation - Season 3",
      "Miss Monochrome: The Animation - Staffel 3",
      "Miss Monochrome: The Animation 3",
      "Мисс Монохром 3",
      "みすものくろーむじあにめーしょんすりー",
      "ミス・モノクローム -The Animation- 3",
      "黑白小姐 第三季"
    ]
  },
  {
    "title": "K RETURN OF KINGS",
    "titleTranslate": {
      "zh-Hans": [
        "K 诸王归来",
        "「K」第二季"
      ],
      "zh-Hant": [
        "K: Return of Kings"
      ],
      "en": [
        "K RETURN OF KINGS"
      ]
    },
    "type": "tv",
    "lang": "ja",
    "officialSite": "http://k-project-come-back.jpn.com/",
    "begin": "2015-10-02T16:55:00.000Z",
    "end": "2015-12-25T17:30:00.000Z",
    "sites": [
      {
        "site": "bilibili",
        "id": "2725",
        "begin": "2015-10-02T18:40:00.000Z",
        "broadcast": "R/2015-10-02T18:40:00.000Z/P7D"
      },
      {
        "site": "bangumi",
        "id": "115917"
      },
      {
        "site": "nicovideo",
        "id": "k-project02",
        "begin": "2015-10-07T13:30:00.000Z",
        "broadcast": "R/2015-10-07T13:30:00.000Z/P7D"
      },
      {
        "site": "unext",
        "id": "SID0020099",
        "begin": "2017-10-05T03:00:00.000Z",
        "broadcast": "R/2017-10-05T03:00:00.000Z/P7D"
      },
      {
        "site": "dmhy",
        "id": "return+of+kings"
      },
      {
        "site": "bangumi_moe",
        "id": "560d0f159286e15329cf94ee"
      },
      {
        "site": "mikan",
        "id": "584"
      }
    ],
    "animeSeason": {
      "season": "FALL",
      "year": 2015,
      "month": "10"
    },
    "status": "FINISHED",
    "episodes": 13,
    "picture": "https://cdn.myanimelist.net/images/anime/6/76198.jpg",
    "thumbnail": "https://cdn.myanimelist.net/images/anime/6/76198t.jpg",
    "synonyms": [
      "K (2015)",
      "K 2nd Season",
      "K : Return of Kings",
      "K RETURN OF KINGS",
      "K Second Season",
      "K Staffel 2",
      "K 诸王归来",
      "K-Project 2",
      "K-Project Sequel",
      "K: RETURN OF KINGS",
      "けいりたーんおぶきんぐす"
    ]
  },
  {
    "title": "落第騎士の英雄譚",
    "titleTranslate": {
      "zh-Hans": [
        "落第骑士英雄谭"
      ],
      "en": [
        "Rakudai Kishi no Cavalry",
        "A tale of worst one"
      ]
    },
    "type": "tv",
    "lang": "ja",
    "officialSite": "http://www.ittoshura.com/",
    "begin": "2015-10-03T14:00:00.000Z",
    "end": "2015-12-19T14:30:00.000Z",
    "sites": [
      {
        "site": "bilibili",
        "id": "2743",
        "begin": "2015-10-03T15:00:00.000Z",
        "broadcast": "R/2015-10-03T15:00:00.000Z/P7D"
      },
      {
        "site": "youku",
        "id": "28181c0256a511e5b5ce",
        "begin": "2015-10-03T15:00:00.000Z"
      },
      {
        "site": "bangumi",
        "id": "127724"
      },
      {
        "site": "nicovideo",
        "id": "ittoshura",
        "begin": "2015-10-06T03:00:00.000Z",
        "broadcast": "R/2015-10-06T03:00:00.000Z/P7D"
      },
      {
        "site": "iqiyi",
        "id": "a_19rrh83ph1",
        "begin": "2017-06-30T16:02:28.000Z"
      },
      {
        "site": "qq",
        "id": "x/x1ad426hnogq7e0",
        "begin": ""
      },
      {
        "site": "acfun",
        "id": "6003941",
        "begin": ""
      },
      {
        "site": "unext",
        "id": "SID0019866",
        "begin": "2015-10-06T03:00:00.000Z",
        "broadcast": "R/2015-10-06T03:00:00.000Z/P7D"
      },
      {
        "site": "dmhy",
        "id": "落第"
      },
      {
        "site": "bangumi_moe",
        "id": "560d11039286e15329cf9504"
      },
      {
        "site": "mikan",
        "id": "591"
      }
    ],
    "animeSeason": {
      "season": "FALL",
      "year": 2015,
      "month": "10"
    },
    "status": "FINISHED",
    "episodes": 12,
    "picture": "https://cdn.myanimelist.net/images/anime/9/76493.jpg",
    "thumbnail": "https://cdn.myanimelist.net/images/anime/9/76493t.jpg",
    "synonyms": [
      "A Chivalry of a Failed Knight",
      "A Chivalry of the Failed Knight",
      "A Tale of Worst One",
      "A Tale of Worst One, Rakudai Kishi no Eiyuutan",
      "A tale of worst one",
      "Cavalry",
      "Chivalry",
      "Chivalry of a Failed Knight",
      "Chivalry of the Failed Knight",
      "L'epopea del cavaliere ripetente",
      "Rakudai Kishi no Eiyuutan",
      "ittoshura",
      "rakudaikishi",
      "Доблестните рицари-неудачници",
      "Доблестният рицар-неудачник",
      "Доблесть Рыцаря-Неудачника",
      "เจ้าหญิงสีชาดกับอัศวินดาบไร้เทียมทาน",
      "落第騎士の英雄譚",
      "落第騎士の英雄譚[キャバルリィ] A TALE OF WORST ONE",
      "落第騎士の英雄譚《キャバルリィ》",
      "落第騎士の英雄譚（キャバルリィ）",
      "落第骑士英雄谭",
      "낙제 기사의 영웅담"
    ]
  },
  {
    "title": "ノラガミ ARAGOTO",
    "titleTranslate": {
      "zh-Hans": [
        "野良神 ARAGOTO",
        "野良神 荒事",
        "流浪神差 第二季",
        "野良神 第二季"
      ],
      "zh-Hant": [
        "流浪神差 ARAGOTO"
      ],
      "en": [
        "NORAGAMI ARAGOTO"
      ]
    },
    "type": "tv",
    "lang": "ja",
    "officialSite": "http://noragami-anime.net/",
    "begin": "2015-10-02T16:05:00.000Z",
    "end": "2015-12-25T18:30:00.000Z",
    "sites": [
      {
        "site": "bilibili",
        "id": "2732",
        "begin": "2015-10-02T17:05:00.000Z",
        "broadcast": "R/2015-10-02T17:05:00.000Z/P7D"
      },
      {
        "site": "bangumi",
        "id": "129988"
      },
      {
        "site": "gamer",
        "id": "76284",
        "begin": "2018-02-14T09:00:00.000Z",
        "broadcast": "R/2018-02-14T09:00:00.000Z/P7D"
      },
      {
        "site": "unext",
        "id": "SID0033207",
        "begin": "2018-04-05T03:00:00.000Z",
        "broadcast": "R/2018-04-05T03:00:00.000Z/P7D"
      },
      {
        "site": "dmhy",
        "id": "良神|Noragami"
      },
      {
        "site": "bangumi_moe",
        "id": "560d0f3a9286e15329cf94f0"
      },
      {
        "site": "mikan",
        "id": "583"
      }
    ],
    "animeSeason": {
      "season": "FALL",
      "year": 2015,
      "month": "10"
    },
    "status": "FINISHED",
    "episodes": 13,
    "picture": "https://cdn.myanimelist.net/images/anime/1689/94850.jpg",
    "thumbnail": "https://cdn.myanimelist.net/images/anime/1689/94850t.jpg",
    "synonyms": [
      "Noragami 2",
      "Noragami ARAGOTO",
      "noragami s2",
      "Бездомный Бог Арагото",
      "โนรางามิ เทวดาขาจร ภาค 2",
      "のらがみあらごと",
      "ノラガミ ARAGOTO",
      "ノラガミ Aragoto",
      "ノラガミ アラゴト",
      "流浪神差ARAGOTO",
      "野良神 ARAGOTO"
    ]
  },
  {
    "title": "学戦都市アスタリスク",
    "titleTranslate": {
      "zh-Hans": [
        "学战都市 阿斯塔利斯克",
        "学战都市Asterisk",
        "学战都市 六芒星"
      ],
      "en": [
        "Gakusen Toshi Asterisk",
        "THE ASTERISK WAR"
      ]
    },
    "type": "tv",
    "lang": "ja",
    "officialSite": "http://asterisk-war.com/",
    "begin": "2015-10-03T11:30:00.000Z",
    "end": "2015-12-19T12:00:00.000Z",
    "sites": [
      {
        "site": "bilibili",
        "id": "2722",
        "begin": "2015-10-03T13:00:00.000Z",
        "broadcast": "R/2015-10-03T13:00:00.000Z/P7D"
      },
      {
        "site": "bangumi",
        "id": "130250"
      },
      {
        "site": "nicovideo",
        "id": "asterisk-war",
        "begin": "2015-10-08T03:00:00.000Z",
        "broadcast": "R/2015-10-08T03:00:00.000Z/P7D"
      },
      {
        "site": "unext",
        "id": "SID0019861",
        "begin": "2019-02-21T03:00:00.000Z",
        "broadcast": "R/2019-02-21T03:00:00.000Z/P7D"
      },
      {
        "site": "dmhy",
        "id": "戰都"
      },
      {
        "site": "bangumi_moe",
        "id": "560d10dc9286e15329cf9502"
      },
      {
        "site": "mikan",
        "id": "590"
      }
    ],
    "animeSeason": {
      "season": "SPRING",
      "year": 2016,
      "month": "10"
    },
    "status": "FINISHED",
    "episodes": 12,
    "picture": "https://cdn.myanimelist.net/images/anime/11/79107.jpg",
    "thumbnail": "https://cdn.myanimelist.net/images/anime/11/79107t.jpg",
    "synonyms": [
      "Academy Battle City Asterisk",
      "Asterisk Savaşı (2016)",
      "Asterisk p2",
      "Gakusen Toshi Asterisk (2016)",
      "Gakusen Toshi Asterisk 2",
      "Gakusen Toshi Asterisk 2nd Part",
      "Gakusen Toshi Asterisk Part 2",
      "The Asterisk War (2016)",
      "The Asterisk War (Part 2)",
      "The Asterisk War 2",
      "The Asterisk War 2nd Saison",
      "The Asterisk War 2nd Season",
      "The Asterisk War 2nd Staffel",
      "The Asterisk War II",
      "The Asterisk War Part 2",
      "The Asterisk War Season 2",
      "The Asterisk War Temporada 2",
      "The Asterisk War: 2. Staffel",
      "The Asterisk War: 2nd Season",
      "The Asterisk War: The Academy City on the Water",
      "The Asterisk War: The Academy City on the Water Arc 2",
      "gta2",
      "Боевая академия города Астериск 2",
      "学战都市Asterisk 第二季",
      "学戦都市アスタリスク",
      "学戦都市アスタリスク (2016)",
      "学戦都市アスタリスク 2",
      "学戦都市アスタリスク 2nd Season",
      "學戰都市Asterisk (2016)"
    ]
  },
  {
    "title": "いとしのムーコ",
    "titleTranslate": {
      "zh-Hans": [
        "家有穆珂",
        "可爱的穆珂"
      ],
      "en": [
        "Itoshi no Muco",
        "Lovely Muuuuuuuco!"
      ]
    },
    "type": "tv",
    "lang": "ja",
    "officialSite": "http://www.anime-muco.com/",
    "begin": "2015-10-03T00:14:00.000Z",
    "end": "2016-03-26T00:30:00.000Z",
    "sites": [
      {
        "site": "bilibili",
        "id": "2794",
        "begin": "2015-10-08T16:05:00.000Z",
        "broadcast": "R/2015-10-07T16:05:00.000Z/P7D"
      },
      {
        "site": "bangumi",
        "id": "131803"
      },
      {
        "site": "dmhy",
        "id": "Muco"
      },
      {
        "site": "bangumi_moe",
        "id": "560d10849286e15329cf94fe"
      },
      {
        "site": "mikan",
        "id": "589"
      },
      {
        "site": "nicovideo",
        "id": "muco",
        "begin": "2020-01-31T15:00:00.000Z",
        "broadcast": "R/2020-01-31T15:00:00.000Z/P7D"
      }
    ],
    "animeSeason": {
      "season": "FALL",
      "year": 2015,
      "month": "10"
    },
    "status": "FINISHED",
    "episodes": 25,
    "picture": "https://cdn.myanimelist.net/images/anime/10/76473.jpg",
    "thumbnail": "https://cdn.myanimelist.net/images/anime/10/76473t.jpg",
    "synonyms": [
      "Itoshi no Muuco",
      "Itoshi no Mūco",
      "Lovely Muco!",
      "Lovely Muuuuuuco!",
      "Lovely Muuuuuuuco!",
      "いとしのむーこ",
      "いとしのムーコ",
      "家有穆珂"
    ]
  },
  {
    "title": "終物語",
    "titleTranslate": {
      "zh-Hans": [
        "终物语"
      ],
      "en": [
        "Owarimonogatari"
      ],
      "zh-Hant": [
        "終物語"
      ]
    },
    "type": "tv",
    "lang": "ja",
    "officialSite": "http://www.monogatari-series.com/owarimonogatari/",
    "begin": "2015-10-03T15:00:00.000Z",
    "end": "2015-12-19T15:30:00.000Z",
    "sites": [
      {
        "site": "bilibili",
        "id": "2747",
        "begin": "2015-10-09T06:00:00.000Z",
        "broadcast": "R/2015-10-04T05:30:00.000Z/P7D"
      },
      {
        "site": "bangumi",
        "id": "138829"
      },
      {
        "site": "nicovideo",
        "id": "owarimonogatari",
        "begin": "2015-10-07T14:30:00.000Z",
        "broadcast": "R/2015-10-07T14:30:00.000Z/P7D"
      },
      {
        "site": "gamer",
        "id": "78087",
        "begin": "2017-01-13T06:20:00.000Z",
        "broadcast": "R/2017-01-13T06:20:00.000Z/P7D"
      },
      {
        "site": "abema",
        "id": "26-2mzbynr-cph",
        "begin": "",
        "broadcast": ""
      },
      {
        "site": "unext",
        "id": "SID0019862",
        "begin": "2018-11-10T03:00:00.000Z",
        "broadcast": "R/2018-11-10T03:00:00.000Z/P7D"
      },
      {
        "site": "dmhy",
        "id": "終物語"
      },
      {
        "site": "bangumi_moe",
        "id": "560d111c9286e15329cf9506"
      },
      {
        "site": "mikan",
        "id": "592"
      }
    ],
    "animeSeason": {
      "season": "FALL",
      "year": 2015,
      "month": "10"
    },
    "status": "FINISHED",
    "episodes": 12,
    "picture": "https://cdn.myanimelist.net/images/anime/8/76479.jpg",
    "thumbnail": "https://cdn.myanimelist.net/images/anime/8/76479t.jpg",
    "synonyms": [
      "End Story",
      "End Tale",
      "Endstory",
      "OMG",
      "mng s7",
      "Истории Последствий",
      "Край на историята",
      "おわりものがたり",
      "終物語",
      "终物语"
    ]
  },
  {
    "title": "ハイキュー!! セカンドシーズン",
    "titleTranslate": {
      "zh-Hans": [
        "排球少年 第二季"
      ],
      "en": [
        "Haikyuu S2"
      ],
      "zh-Hant": [
        "排球少年!! 第二季",
        "排球少年！！第二季"
      ]
    },
    "type": "tv",
    "lang": "ja",
    "officialSite": "http://www.j-haikyu.com/anime/",
    "begin": "2015-10-03T17:58:00.000Z",
    "end": "2016-03-26T18:28:00.000Z",
    "sites": [
      {
        "site": "youku",
        "id": "8cc9553c560d11e5b432",
        "begin": "2015-10-03T18:30:00.000Z"
      },
      {
        "site": "bangumi",
        "id": "120236"
      },
      {
        "site": "ani_one_asia",
        "id": "PLxSscENEp7Jh1Q9eywt3xbryU2shwg488",
        "begin": "2021-08-09T16:00:00.000Z",
        "broadcast": "R/2021-08-09T16:00:00.000Z/P7D"
      },
      {
        "site": "ani_one",
        "id": "PLC18xlbCdwtRKmhxiP7IygtqmGNbDQ0DR",
        "begin": "2022-09-20T16:00:00.000Z",
        "broadcast": "R/2022-09-20T16:00:00.000Z/P7D"
      },
      {
        "site": "disneyplus",
        "id": "7iGL15MOs7hZ",
        "begin": "",
        "broadcast": ""
      },
      {
        "site": "gamer",
        "id": "74666",
        "begin": "2021-12-10T05:00:00.000Z",
        "broadcast": "R/2021-12-10T05:00:00.000Z/P7D"
      },
      {
        "site": "abema",
        "id": "19-16",
        "begin": "",
        "broadcast": ""
      },
      {
        "site": "unext",
        "id": "SID0020198",
        "begin": "2018-04-29T03:00:00.000Z",
        "broadcast": "R/2018-04-29T03:00:00.000Z/P7D"
      },
      {
        "site": "gamer_hk",
        "id": "74666",
        "begin": "2021-12-10T05:00:00.000Z",
        "broadcast": "R/2021-12-10T05:00:00.000Z/P7D"
      },
      {
        "site": "mikan",
        "id": "595"
      },
      {
        "site": "nicovideo",
        "id": "haikyu02",
        "begin": "2015-10-14T03:00:00.000Z",
        "broadcast": "R/2015-10-14T03:00:00.000Z/P7D"
      }
    ],
    "animeSeason": {
      "season": "FALL",
      "year": 2015,
      "month": "10"
    },
    "status": "FINISHED",
    "episodes": 25,
    "picture": "https://cdn.myanimelist.net/images/anime/9/76662.jpg",
    "thumbnail": "https://cdn.myanimelist.net/images/anime/9/76662t.jpg",
    "synonyms": [
      "HAIKYU!! 2nd Season",
      "HAIKYU!! Second Season",
      "HQ!! 2",
      "Haikyu!! 2",
      "Haikyu!! 2da Temporada",
      "Haikyu!! 2nd Season",
      "Haikyu!! Los Ases del Vóley 2ª temporada",
      "Haikyu!! Los Ases del Vóley Temporada 2",
      "Haikyu!! L’Asso del Volley 2",
      "Haikyu!! Saison 2",
      "Haikyu!! Staffel 2",
      "Haikyu!! Zweite Staffel",
      "Haikyuu - Segunda Temporada",
      "Haikyuu!! 2",
      "Haikyuu!! 2nd Season",
      "Haikyuu!! II",
      "Haikyuu2",
      "Haikyū!! Second Season",
      "Волейбол!! [ТВ-2]",
      "ไฮคิว!! คู่ตบฟ้าประทาน ภาค 2",
      "はいきゅーせかんどしーずん",
      "ハイキュー!! セカンドシーズン",
      "ハイキュー！！ セカンドシーズン",
      "排球少年 第二季"
    ]
  },
  {
    "title": "うたわれるもの 偽りの仮面",
    "titleTranslate": {
      "zh-Hans": [
        "传颂之物 虚伪的假面"
      ],
      "en": [
        "Utawarerumono - Itsuwari no Kamen"
      ]
    },
    "type": "tv",
    "lang": "ja",
    "officialSite": "http://utawarerumono.jp/",
    "begin": "2015-10-03T16:00:00.000Z",
    "end": "2016-03-26T16:30:00.000Z",
    "sites": [
      {
        "site": "bangumi",
        "id": "136336"
      },
      {
        "site": "nicovideo",
        "id": "utawarerumono02",
        "begin": "2015-10-09T15:00:00.000Z",
        "broadcast": "R/2015-10-09T15:00:00.000Z/P7D"
      },
      {
        "site": "unext",
        "id": "SID0020390",
        "begin": "2015-10-10T03:00:00.000Z",
        "broadcast": "R/2015-10-10T03:00:00.000Z/P7D"
      },
      {
        "site": "dmhy",
        "id": "頌+面"
      },
      {
        "site": "bangumi_moe",
        "id": "560d113e9286e15329cf9508"
      },
      {
        "site": "mikan",
        "id": "587"
      }
    ],
    "animeSeason": {
      "season": "FALL",
      "year": 2015,
      "month": "10"
    },
    "status": "FINISHED",
    "episodes": 25,
    "picture": "https://cdn.myanimelist.net/images/anime/8/75968.jpg",
    "thumbnail": "https://cdn.myanimelist.net/images/anime/8/75968t.jpg",
    "synonyms": [
      "Le Chant des Rêves : Le Masque de l’imposture",
      "Le chant des rêves : Le masque de l`imposture",
      "Utawarerumono The False Faces",
      "Utawarerumono: Mask of Deception",
      "Utawarerumono: The False Faces",
      "Utawarerumono: The False Mask",
      "uwm2",
      "うたわれるもの 偽りの仮面",
      "うたわれるものいつわりのかめん",
      "传颂之物 虚伪的假面",
      "受讚頌者 虛偽的假面"
    ]
  },
  {
    "title": "こわぼん",
    "titleTranslate": {
      "zh-Hans": [
        "KOWABON"
      ],
      "en": [
        "Kowabon",
        "KOWABON"
      ]
    },
    "type": "tv",
    "lang": "ja",
    "officialSite": "http://www.kbc.co.jp/kowabon/index.html",
    "begin": "2015-10-09T16:55:00.000Z",
    "end": "2016-01-01T17:05:00.000Z",
    "sites": [
      {
        "site": "bangumi",
        "id": "136764"
      },
      {
        "site": "unext",
        "id": "SID0020197",
        "begin": "2019-05-01T03:00:00.000Z",
        "broadcast": "R/2019-05-01T03:00:00.000Z/P7D"
      },
      {
        "site": "dmhy",
        "id": "Kowabon"
      },
      {
        "site": "bangumi_moe",
        "id": "560d11529286e15329cf950a"
      },
      {
        "site": "mikan",
        "id": "593"
      }
    ],
    "animeSeason": {
      "season": "FALL",
      "year": 2015,
      "month": "10"
    },
    "status": "FINISHED",
    "episodes": 13,
    "picture": "https://cdn.myanimelist.net/images/anime/1695/112630.jpg",
    "thumbnail": "https://cdn.myanimelist.net/images/anime/1695/112630t.jpg",
    "synonyms": [
      "KOWABON",
      "こわぼん"
    ]
  },
  {
    "title": "小森さんは断れない！",
    "titleTranslate": {
      "zh-Hans": [
        "小森同学拒绝不了！",
        "小森拒不了！"
      ],
      "en": [
        "Komori-san wa Kotowarenai"
      ]
    },
    "type": "tv",
    "lang": "ja",
    "officialSite": "http://komori-anime.com/",
    "begin": "2015-10-04T13:27:00.000Z",
    "end": "2015-12-20T13:30:00.000Z",
    "sites": [
      {
        "site": "bilibili",
        "id": "2744",
        "begin": "2015-10-04T14:00:00.000Z",
        "broadcast": "R/2015-10-04T14:00:00.000Z/P7D"
      },
      {
        "site": "bangumi",
        "id": "138205"
      },
      {
        "site": "nicovideo",
        "id": "komori-anime",
        "begin": "2015-10-11T13:00:00.000Z",
        "broadcast": "R/2015-10-11T13:00:00.000Z/P7D"
      },
      {
        "site": "unext",
        "id": "SID0042775",
        "begin": "2019-10-24T03:00:00.000Z",
        "broadcast": "R/2019-10-24T03:00:00.000Z/P7D"
      },
      {
        "site": "dmhy",
        "id": "森拒"
      },
      {
        "site": "bangumi_moe",
        "id": "560d12b99286e15329cf951c"
      },
      {
        "site": "mikan",
        "id": "600"
      }
    ],
    "animeSeason": {
      "season": "FALL",
      "year": 2015,
      "month": "10"
    },
    "status": "FINISHED",
    "episodes": 12,
    "picture": "https://cdn.myanimelist.net/images/anime/7/78082.jpg",
    "thumbnail": "https://cdn.myanimelist.net/images/anime/7/78082t.jpg",
    "synonyms": [
      "Komori Can’t Refuse!",
      "Komori-san Can't Decline!",
      "Komori-san Can't Decline!: Komori-san wa Kotowarenai!",
      "Komori-san Can`t Decline!",
      "Komori-san Can’t Decline!",
      "Komori-san kann nicht Nein sagen!",
      "こもりさんはことわれない",
      "小森さんは断れない!",
      "小森さんは断れない！",
      "小森同学拒绝不了！"
    ]
  },
  {
    "title": "雨色ココア Rainy colorへようこそ！",
    "titleTranslate": {
      "zh-Hans": [
        "雨色可可 欢迎来到Rainy color！",
        "雨色可可 第二季"
      ],
      "en": [
        "Rainy cocoa Rainy color",
        "Ame-iro Cocoa - Rainy Color e Youkoso"
      ]
    },
    "type": "tv",
    "lang": "ja",
    "officialSite": "http://rainycocoa.jp/anime/",
    "begin": "2015-10-04T13:15:00.000Z",
    "end": "2015-10-18T13:27:00.000Z",
    "sites": [
      {
        "site": "bilibili",
        "id": "2763",
        "begin": "2015-10-04T15:15:00.000Z",
        "broadcast": "R/2015-10-04T15:15:00.000Z/P7D"
      },
      {
        "site": "bangumi",
        "id": "138834"
      },
      {
        "site": "nicovideo",
        "id": "rainycocoa2",
        "begin": "2015-10-05T15:00:00.000Z",
        "broadcast": "R/2015-10-05T15:00:00.000Z/P7D"
      },
      {
        "site": "unext",
        "id": "SID0020096",
        "begin": "2022-02-01T03:00:00.000Z",
        "broadcast": "R/2022-02-01T03:00:00.000Z/P7D"
      },
      {
        "site": "bangumi_moe",
        "id": "560d12a09286e15329cf951a"
      },
      {
        "site": "mikan",
        "id": "599"
      }
    ],
    "animeSeason": {
      "season": "FALL",
      "year": 2015,
      "month": "10"
    },
    "status": "FINISHED",
    "episodes": 12,
    "picture": "https://cdn.myanimelist.net/images/anime/1065/111717.jpg",
    "thumbnail": "https://cdn.myanimelist.net/images/anime/1065/111717t.jpg",
    "synonyms": [
      "Ame-iro Cocoa 2",
      "Ame-iro Cocoa: Rainy Color e Youkoso",
      "Ame-iro Cocoa: Rainy Color e Yōkoso!",
      "Ame-iro Cocoa: Rainy color e Youkoso!",
      "Ameiro Cocoa Season 2",
      "Ameiro Cocoa: Rainy Color e Youkoso!",
      "Ameiro Cocoa: Rainy color e Youkoso!",
      "Rainy Cocoa",
      "Rainy Cocoa Second Season",
      "Rainy Cocoa, Welcome to Rainy Color",
      "Rainy Cocoa: Season 2",
      "Rainy Cocoa: Temporada 2",
      "Rainy Cocoa: Welcome to Rainy Color",
      "あめいろここあれいにーからーへようこそ",
      "雨色ココア Rainy colorへようこそ!",
      "雨色ココア Rainy colorへようこそ！",
      "雨色可可 欢迎来到Rainy color！"
    ]
  },
  {
    "title": "温泉幼精ハコネちゃん",
    "titleTranslate": {
      "zh-Hans": [
        "温泉幼精小箱根",
        "温泉幼精箱根酱"
      ],
      "en": [
        "Onsen Yousei Hakone-chan"
      ]
    },
    "type": "tv",
    "lang": "ja",
    "officialSite": "http://www.hakone-chan.jp/",
    "begin": "2015-10-04T11:55:00.000Z",
    "end": "2015-12-27T12:00:00.000Z",
    "sites": [
      {
        "site": "bilibili",
        "id": "2729",
        "begin": "2015-10-04T16:05:00.000Z",
        "broadcast": "R/2015-10-04T16:05:00.000Z/P7D"
      },
      {
        "site": "iqiyi",
        "id": "a_19rrhbax91",
        "begin": "2015-10-04T16:05:00.000Z"
      },
      {
        "site": "youku",
        "id": "26ba1dc456b911e5b432",
        "begin": "2015-10-04T16:05:00.000Z"
      },
      {
        "site": "bangumi",
        "id": "138960"
      },
      {
        "site": "nicovideo",
        "id": "hakone-chan",
        "begin": "2015-10-09T03:00:00.000Z",
        "broadcast": "R/2015-10-09T03:00:00.000Z/P7D"
      },
      {
        "site": "dmhy",
        "id": "幼精"
      },
      {
        "site": "bangumi_moe",
        "id": "560d128b9286e15329cf9518"
      },
      {
        "site": "mikan",
        "id": "598"
      }
    ],
    "animeSeason": {
      "season": "FALL",
      "year": 2015,
      "month": "10"
    },
    "status": "FINISHED",
    "episodes": 13,
    "picture": "https://cdn.myanimelist.net/images/anime/12/77820.jpg",
    "thumbnail": "https://cdn.myanimelist.net/images/anime/12/77820t.jpg",
    "synonyms": [
      "Hakone",
      "Hakone-Chan",
      "Hakone-chan",
      "Hot Springs Fairy Hakone-Chan",
      "Onsen Yôsei Hakone-chan",
      "Onsen Yōsei Hakone-chan",
      "Young Hot Spring Spirit Hakone-chan",
      "Юный дух горячего источника Хаконе-тян",
      "おんせんようせいハコネちゃん",
      "温泉幼精ハコネちゃん",
      "温泉幼精箱根酱"
    ]
  },
  {
    "title": "コンクリート・レボルティオ～超人幻想～",
    "titleTranslate": {
      "zh-Hans": [
        "Concrete Revolutio 超人幻想",
        "混凝土革命 超人幻想"
      ],
      "en": [
        "Concrete Revolutio A Superhuman Fantasy"
      ]
    },
    "type": "tv",
    "lang": "ja",
    "officialSite": "http://concreterevolutio.com/",
    "begin": "2015-10-04T14:00:00.000Z",
    "end": "2015-12-27T14:30:00.000Z",
    "sites": [
      {
        "site": "bilibili",
        "id": "2741",
        "begin": "2015-10-04T14:30:00.000Z",
        "broadcast": "R/2015-10-04T14:30:00.000Z/P7D"
      },
      {
        "site": "youku",
        "id": "189c428856bb11e5b432",
        "begin": "2015-10-04T14:30:00.000Z"
      },
      {
        "site": "bangumi",
        "id": "139022"
      },
      {
        "site": "iqiyi",
        "id": "a_19rrh82u99",
        "begin": "2017-06-30T16:02:42.000Z"
      },
      {
        "site": "qq",
        "id": "a/aal134p96a0g3us",
        "begin": ""
      },
      {
        "site": "dmhy",
        "id": "超人幻|Concrete"
      },
      {
        "site": "bangumi_moe",
        "id": "560d132e9286e15329cf9520"
      },
      {
        "site": "mikan",
        "id": "602"
      }
    ],
    "animeSeason": {
      "season": "FALL",
      "year": 2015,
      "month": "10"
    },
    "status": "FINISHED",
    "episodes": 13,
    "picture": "https://cdn.myanimelist.net/images/anime/3/76143.jpg",
    "thumbnail": "https://cdn.myanimelist.net/images/anime/3/76143t.jpg",
    "synonyms": [
      "ConRevo",
      "Concrete Revolutio",
      "Concrete Revolutio: Chōjin Gensō",
      "Concrete Revolutio: Superhuman Phantasmagoria",
      "こんくりーとれぼるてぃおちょうじんげんそう",
      "コンクリート・レボルティオ 超人幻想",
      "コンクリート・レボルティオ～超人幻想～",
      "具象革命 超人幻想",
      "콘크리트 레볼루티오 초인환상"
    ]
  },
  {
    "title": "機動戦士ガンダム 鉄血のオルフェンズ",
    "titleTranslate": {
      "zh-Hans": [
        "机动战士高达 铁血的奥尔芬斯",
        "机动战士高达 铁血的孤儿"
      ],
      "zh-Hant": [
        "機動戰士鋼彈：鐵血孤兒",
        "機動戰士高達 鐵血的孤兒"
      ],
      "en": [
        "Mobile Suit Gundam Tekketsu no Orphans",
        "Mobile Suit Gundam: Iron-Blooded Orphans"
      ]
    },
    "type": "tv",
    "lang": "ja",
    "officialSite": "http://g-tekketsu.com/1st/",
    "begin": "2015-10-04T08:00:00.000Z",
    "end": "2016-03-27T09:00:00.000Z",
    "sites": [
      {
        "site": "youku",
        "id": "2c1e303055f011e5a080",
        "begin": "2015-10-04T10:30:00.000Z"
      },
      {
        "site": "bilibili",
        "id": "4310042",
        "begin": "2015-10-04T10:30:00.000Z",
        "broadcast": "R/2018-11-16T10:00:00.000Z/P7D"
      },
      {
        "site": "bangumi",
        "id": "139324"
      },
      {
        "site": "unext",
        "id": "SID0027096",
        "begin": "2016-10-23T03:00:00.000Z",
        "broadcast": "R/2016-10-23T03:00:00.000Z/P7D",
        "comment": "第26話～: SID0027097"
      },
      {
        "site": "dmhy",
        "id": "機動+鐵血"
      },
      {
        "site": "bangumi_moe",
        "id": "560d12549286e15329cf9516"
      },
      {
        "site": "mikan",
        "id": "597"
      }
    ],
    "animeSeason": {
      "season": "FALL",
      "year": 2015,
      "month": "10"
    },
    "status": "FINISHED",
    "episodes": 25,
    "picture": "https://cdn.myanimelist.net/images/anime/6/75879.jpg",
    "thumbnail": "https://cdn.myanimelist.net/images/anime/6/75879t.jpg",
    "synonyms": [
      "G-Tekketsu",
      "Gundam IBO",
      "Gundam: Sirotci s železnou krví",
      "Gundam: Tekketsu no Orphans",
      "Kidō Senshi Gundam: Tekketsu no Orphans",
      "Mobile Suit GUNDAM Iron Blooded Orphans",
      "Mobile Suit Gundam : Iron-Blooded Orphans",
      "Mobile Suit Gundam Iron Blooded Orphans",
      "Mobile Suit Gundam: Iron Blooded Orphans",
      "Mobile Suit Gundam: Iron-Blooded Orphans",
      "iron blooded orphans",
      "Мобилни костюми Гъндам: Сираци от кръв и желязо",
      "חליפה ניידת גנדאם: יתומי דם ברזל",
      "きどうせんしがんだむてっけつのおるふぇんず",
      "机动战士高达 铁血的奥尔芬斯",
      "机动战士高达 铁血的孤儿",
      "機動戦士ガンダム 鉄血のオルフェンズ",
      "기동전사 건담: 철혈의 오펀스"
    ]
  },
  {
    "title": "コメット・ルシファー",
    "titleTranslate": {
      "zh-Hans": [
        "彗星路西法"
      ],
      "en": [
        "Comet Lucifer"
      ],
      "zh-Hant": [
        "彗星路西法"
      ]
    },
    "type": "tv",
    "lang": "ja",
    "officialSite": "http://comet-lucifer.jp/",
    "begin": "2015-10-04T13:30:00.000Z",
    "end": "2015-12-20T14:00:00.000Z",
    "sites": [
      {
        "site": "bilibili",
        "id": "2745",
        "begin": "2015-10-04T14:30:00.000Z",
        "broadcast": "R/2015-10-04T14:30:00.000Z/P7D"
      },
      {
        "site": "youku",
        "id": "a19a996458ef11e5b692",
        "begin": "2015-10-04T14:30:00.000Z"
      },
      {
        "site": "bangumi",
        "id": "141225"
      },
      {
        "site": "iqiyi",
        "id": "a_19rrh84jt1",
        "begin": "2017-06-30T16:02:42.000Z"
      },
      {
        "site": "qq",
        "id": "i/isisk8elvk0xrtw",
        "begin": ""
      },
      {
        "site": "ani_one_asia",
        "id": "PLxSscENEp7Jjp_83xN-2ErQpJkjlH5rna",
        "begin": "2023-03-24T16:00:00.000Z",
        "broadcast": "R/2023-03-24T16:00:00.000Z/P7D"
      },
      {
        "site": "gamer",
        "id": "78527",
        "begin": "2017-06-20T09:00:00.000Z",
        "broadcast": "R/2017-06-20T09:00:00.000Z/P7D"
      },
      {
        "site": "dmhy",
        "id": "路西法|lucifer"
      },
      {
        "site": "bangumi_moe",
        "id": "560d12c49286e15329cf951e"
      },
      {
        "site": "mikan",
        "id": "601"
      }
    ],
    "animeSeason": {
      "season": "FALL",
      "year": 2015,
      "month": "10"
    },
    "status": "FINISHED",
    "episodes": 12,
    "picture": "https://cdn.myanimelist.net/images/anime/3/76111.jpg",
    "thumbnail": "https://cdn.myanimelist.net/images/anime/3/76111t.jpg",
    "synonyms": [
      "cometlucifer",
      "Комета Люцифер",
      "こめっとるしふぁー",
      "コメット・ルシファー",
      "彗星路西法",
      "코멧 루시퍼"
    ]
  },
  {
    "title": "進撃！巨人中学校",
    "titleTranslate": {
      "zh-Hans": [
        "进击！巨人中学",
        "进击！巨人中学校",
        "最强中学"
      ],
      "en": [
        "Shingeki! Kyojin Chuugakkou"
      ]
    },
    "type": "tv",
    "lang": "ja",
    "officialSite": "http://kyojinchu.tv/",
    "begin": "2015-10-03T16:58:00.000Z",
    "end": "2015-12-19T17:28:00.000Z",
    "sites": [
      {
        "site": "youku",
        "id": "a29bac3c575e11e5b432",
        "begin": "2015-10-03T21:30:00.000Z"
      },
      {
        "site": "iqiyi",
        "id": "a_19rrhbb1sl",
        "begin": "2015-10-03T21:30:00.000Z"
      },
      {
        "site": "bangumi",
        "id": "141781"
      },
      {
        "site": "nicovideo",
        "id": "kyojinchu",
        "begin": "2015-10-05T16:50:00.000Z",
        "broadcast": "R/2015-10-05T16:50:00.000Z/P7D"
      },
      {
        "site": "unext",
        "id": "SID0020089",
        "begin": "2015-10-05T03:00:00.000Z",
        "broadcast": "R/2015-10-05T03:00:00.000Z/P7D"
      },
      {
        "site": "dmhy",
        "id": "進+中學"
      },
      {
        "site": "bangumi_moe",
        "id": "560d11809286e15329cf950c"
      },
      {
        "site": "mikan",
        "id": "594"
      }
    ],
    "animeSeason": {
      "season": "FALL",
      "year": 2015,
      "month": "10"
    },
    "status": "FINISHED",
    "episodes": 12,
    "picture": "https://cdn.myanimelist.net/images/anime/3/75467.jpg",
    "thumbnail": "https://cdn.myanimelist.net/images/anime/3/75467t.jpg",
    "synonyms": [
      "Ataque a los Titanes: Junior High",
      "Attack on Titan: Junior High",
      "Attack! Titan Junior High",
      "Attaque des Titans Junior High-school",
      "L`Attaque Des Titans Junior High-School",
      "Shingeki! Kyojin Chūgakkō",
      "snk (2015)",
      "ผ่า! มัธยมไททัน",
      "ผ่ามัธยมไททัน",
      "しんげききょじんちゅうがっこう",
      "进击! 巨人中学校",
      "進撃! 巨人中学校",
      "進撃! 巨人中学校 attack on titan: junior high",
      "進撃！ 巨人中学校",
      "進撃！巨人中学校"
    ]
  },
  {
    "title": "ワンパンマン",
    "titleTranslate": {
      "zh-Hans": [
        "一拳超人",
        "一击男"
      ],
      "en": [
        "One Punch Man",
        "ONE PANCH MAN"
      ],
      "zh-Hant": [
        "一拳超人",
        "一拳超人 (第一季)"
      ]
    },
    "type": "tv",
    "lang": "ja",
    "officialSite": "http://onepunchman-anime.net/",
    "begin": "2015-10-04T16:05:00.000Z",
    "end": "2015-12-20T16:35:00.000Z",
    "sites": [
      {
        "site": "youku",
        "id": "0b39c5b6569311e5b2ad",
        "begin": "2015-10-04T18:00:00.000Z"
      },
      {
        "site": "bangumi",
        "id": "127563"
      },
      {
        "site": "netflix",
        "id": "80117291",
        "begin": "2017-03-20T07:00:00.000Z",
        "broadcast": "R/2022-05-30T16:00:00.000Z/P7D"
      },
      {
        "site": "muse_hk",
        "id": "PLuxqoToY7UchDbGo2TvlrSeB2oFvlx6VU",
        "begin": "2022-01-14T16:00:00.000Z",
        "broadcast": "R/2022-01-14T16:00:00.000Z/P7D"
      },
      {
        "site": "viu",
        "id": "462756",
        "begin": "2022-11-17T16:00:00.000Z",
        "broadcast": "R/2022-11-17T16:00:00.000Z/P7D",
        "comment": "粵語版: 462771"
      },
      {
        "site": "gamer",
        "id": "75930",
        "begin": "2016-01-06T06:46:00.000Z",
        "broadcast": "R/2016-01-06T06:46:00.000Z/P7D"
      },
      {
        "site": "abema",
        "id": "420-14",
        "begin": "",
        "broadcast": ""
      },
      {
        "site": "unext",
        "id": "SID0020051",
        "begin": "2024-03-01T03:00:00.000Z",
        "broadcast": "R/2024-03-01T03:00:00.000Z/P7D"
      },
      {
        "site": "disneyplus",
        "id": "1x8GPWt9gtZ5",
        "begin": "",
        "broadcast": ""
      },
      {
        "site": "gamer_hk",
        "id": "75930",
        "begin": "2016-01-06T06:46:00.000Z",
        "broadcast": "R/2016-01-06T06:46:00.000Z/P7D"
      },
      {
        "site": "dmhy",
        "id": "一拳"
      },
      {
        "site": "bangumi_moe",
        "id": "560d13639286e15329cf9522"
      },
      {
        "site": "mikan",
        "id": "603"
      },
      {
        "site": "nicovideo",
        "id": "onepunchman",
        "begin": "2019-04-11T03:00:00.000Z",
        "broadcast": "R/2019-04-11T03:00:00.000Z/P7D"
      }
    ],
    "animeSeason": {
      "season": "SPRING",
      "year": 2019,
      "month": "10"
    },
    "status": "FINISHED",
    "episodes": 12,
    "picture": "https://cdn.myanimelist.net/images/anime/1247/122044.jpg",
    "thumbnail": "https://cdn.myanimelist.net/images/anime/1247/122044t.jpg",
    "synonyms": [
      "Jagoan Sekali Pukul S2",
      "ONE PUNCH MAN ワンパンマン (2019)",
      "OPM 2",
      "OPM2",
      "One Punch Man (2019)",
      "One Punch Man 2",
      "One Punch Man S2",
      "One Punch Man Saison 2",
      "One Punch Man Season 2",
      "One Punch Man Staffel 2",
      "One Punch Man Temporada 2",
      "One Punch-Man 2",
      "One-Punch Man 2",
      "One-Punch Man Phần 2",
      "One-Punch Man Saison 2",
      "One-Punch Man Season 2",
      "One-Punch Man: Season 2",
      "Wanpanman 2",
      "opm2",
      "Ванпанчмен (2 сезон)",
      "Уанпънч-мен 2",
      "איש האגרוף הבודד (2019)",
      "رجل اللكمة الواحدة (2019)",
      "رجل اللكمة الواحدة 2",
      "مرد تک مشتی",
      "ون بنش مان 2",
      "วันพันช์แมน ภาคที่ 2",
      "わんぱんまん",
      "ワンパンマン",
      "ワンパンマン 2",
      "ワンパンマン SEASON 2",
      "ワンパンマン SEASON2",
      "ワンパンマン(第2期)",
      "一拳超人 第二季",
      "원펀맨 시즌 2"
    ]
  },
  {
    "title": "緋弾のアリアAA",
    "titleTranslate": {
      "zh-Hans": [
        "绯弹的亚里亚AA"
      ],
      "en": [
        "Hidan no Aria AA",
        "Aria the Scarlet Ammo Double A"
      ]
    },
    "type": "tv",
    "lang": "ja",
    "officialSite": "http://ariaaa.tv/",
    "begin": "2015-10-06T14:00:00.000Z",
    "end": "2015-12-22T14:30:00.000Z",
    "sites": [
      {
        "site": "bilibili",
        "id": "2764",
        "begin": "2015-10-06T14:30:00.000Z",
        "broadcast": "R/2015-10-06T14:30:00.000Z/P7D"
      },
      {
        "site": "bangumi",
        "id": "120224"
      },
      {
        "site": "nicovideo",
        "id": "ariaaa",
        "begin": "2015-10-15T14:00:00.000Z",
        "broadcast": "R/2015-10-15T14:00:00.000Z/P7D"
      },
      {
        "site": "unext",
        "id": "SID0020277",
        "begin": "2019-11-03T03:00:00.000Z",
        "broadcast": "R/2019-11-03T03:00:00.000Z/P7D"
      },
      {
        "site": "dmhy",
        "id": "緋彈 AA"
      },
      {
        "site": "bangumi_moe",
        "id": "560d0ce39286e15329cf94ce"
      },
      {
        "site": "mikan",
        "id": "610"
      }
    ],
    "animeSeason": {
      "season": "FALL",
      "year": 2015,
      "month": "10"
    },
    "status": "FINISHED",
    "episodes": 12,
    "picture": "https://cdn.myanimelist.net/images/anime/12/76700.jpg",
    "thumbnail": "https://cdn.myanimelist.net/images/anime/12/76700t.jpg",
    "synonyms": [
      "Aria the Scarlet Ammo AA",
      "Aria the Scarlet Ammo Double A",
      "Hidan no Aria Double A",
      "hna2",
      "Ария по прозвищу \"Алая Пуля\" АА",
      "緋弾のアリアAA",
      "緋弾のアリアAA（ダブルエー）",
      "绯弹的亚里亚AA"
    ]
  },
  {
    "title": "ゆるゆり さん☆ハイ！",
    "titleTranslate": {
      "zh-Hans": [
        "摇曳百合 3☆High!",
        "摇曳百合 第三季"
      ],
      "en": [
        "YRYR TV ANIMATION SERIES SEASON THREE"
      ]
    },
    "type": "tv",
    "lang": "ja",
    "officialSite": "http://yuruyuri.com/3hai/",
    "begin": "2015-10-05T17:05:00.000Z",
    "end": "2015-12-21T17:35:00.000Z",
    "sites": [
      {
        "site": "youku",
        "id": "3d7c3ba456a111e5b522",
        "begin": "2015-10-05T18:05:00.000Z"
      },
      {
        "site": "bangumi",
        "id": "127573"
      },
      {
        "site": "nicovideo",
        "id": "3hai",
        "begin": "2015-10-12T03:00:00.000Z",
        "broadcast": "R/2015-10-12T03:00:00.000Z/P7D"
      },
      {
        "site": "unext",
        "id": "SID0020091",
        "begin": "2015-10-12T03:00:00.000Z",
        "broadcast": "R/2015-10-12T03:00:00.000Z/P7D"
      },
      {
        "site": "abema",
        "id": "149-28i9ircg5g9",
        "begin": "",
        "broadcast": ""
      },
      {
        "site": "dmhy",
        "id": "鬆百|曳百"
      },
      {
        "site": "bangumi_moe",
        "id": "560d0cb19286e15329cf94c8"
      },
      {
        "site": "mikan",
        "id": "607"
      }
    ],
    "animeSeason": {
      "season": "FALL",
      "year": 2015,
      "month": "10"
    },
    "status": "FINISHED",
    "episodes": 12,
    "picture": "https://cdn.myanimelist.net/images/anime/7/76667.jpg",
    "thumbnail": "https://cdn.myanimelist.net/images/anime/7/76667t.jpg",
    "synonyms": [
      "YRYR 3",
      "Yuru Yuri 3",
      "Yuru Yuri 3rd Season",
      "Yuru Yuri Saison 3",
      "Yuru Yuri San Hai!",
      "Yuru Yuri Season 3",
      "Yuru Yuri Temporada 3",
      "Yuru Yuri Third Season",
      "Yuru Yuri-san High!",
      "Yuru Yuri-san High!: YuruYuri S3",
      "Yuru Yuri: Staffel 3",
      "YuruYuri Season 3",
      "YuruYuri Temporada 3",
      "Yuruyuri (Saison 3)",
      "Yuruyuri Season 3",
      "Yuruyuri: Season 3",
      "yuri3",
      "ゆるゆり さん☆はい！",
      "ゆるゆり さん☆ハイ!",
      "ゆるゆり さん☆ハイ！",
      "ゆるゆり 第３期",
      "ゆるゆりさんはい",
      "摇曳百合 3☆High!"
    ]
  },
  {
    "title": "新あたしンち",
    "titleTranslate": {
      "zh-Hans": [
        "我们这一家 新篇",
        "新我们这一家",
        "新 我们这一家"
      ],
      "en": [
        "Shin Atashinchi"
      ]
    },
    "type": "tv",
    "lang": "ja",
    "officialSite": "http://www.animax.co.jp/special/atashinchi/",
    "begin": "2015-10-06T10:00:00.000Z",
    "end": "2016-04-05T10:30:00.000Z",
    "sites": [
      {
        "site": "iqiyi",
        "id": "a_19rrhary39",
        "begin": "2016-07-13T08:52:11.000Z"
      },
      {
        "site": "bilibili",
        "id": "2771",
        "begin": "2015-10-06T10:30:00.000Z",
        "broadcast": "R/2015-10-06T11:30:00.000Z/P7D"
      },
      {
        "site": "youku",
        "id": "a68531045c1f11e5b522",
        "begin": "2015-10-06T10:30:00.000Z"
      },
      {
        "site": "bangumi",
        "id": "131717"
      },
      {
        "site": "abema",
        "id": "35-3",
        "begin": "",
        "broadcast": ""
      },
      {
        "site": "unext",
        "id": "SID0021348",
        "begin": "2016-01-20T03:00:00.000Z",
        "broadcast": "R/2016-01-20T03:00:00.000Z/P7D"
      },
      {
        "site": "dmhy",
        "id": "們這一"
      },
      {
        "site": "mikan",
        "id": "609"
      }
    ],
    "animeSeason": {
      "season": "FALL",
      "year": 2015,
      "month": "10"
    },
    "status": "FINISHED",
    "episodes": 26,
    "picture": "https://cdn.myanimelist.net/images/anime/12/76046.jpg",
    "thumbnail": "https://cdn.myanimelist.net/images/anime/12/76046t.jpg",
    "synonyms": [
      "New Atashin'chi",
      "New Atashinchi",
      "Shin Atashinchi",
      "しんあたしんち",
      "新あたしンち",
      "新我们这一家"
    ]
  },
  {
    "title": "おそ松さん",
    "titleTranslate": {
      "zh-Hans": [
        "阿松",
        "小松先生"
      ],
      "en": [
        "Osomatsu-san"
      ],
      "zh-Hant": [
        "阿松"
      ]
    },
    "type": "tv",
    "lang": "ja",
    "officialSite": "http://osomatsusan.com/",
    "begin": "2015-10-05T16:35:00.000Z",
    "end": "2016-03-28T17:05:00.000Z",
    "sites": [
      {
        "site": "youku",
        "id": "bd38b4fa58f711e5b5ce",
        "begin": "2015-10-05T17:35:00.000Z"
      },
      {
        "site": "bangumi",
        "id": "139408"
      },
      {
        "site": "nicovideo",
        "id": "osomatsusan",
        "begin": "2015-10-18T15:30:00.000Z",
        "broadcast": "R/2015-10-18T15:30:00.000Z/P7D"
      },
      {
        "site": "gamer",
        "id": "78260",
        "begin": "2020-09-14T09:30:00.000Z",
        "broadcast": "R/2020-09-14T09:30:00.000Z/P7D"
      },
      {
        "site": "unext",
        "id": "SID0020090",
        "begin": "2015-10-19T03:00:00.000Z",
        "broadcast": "R/2015-10-19T03:00:00.000Z/P7D",
        "comment": "ショートフィルムシリーズ: SID0028925"
      },
      {
        "site": "gamer_hk",
        "id": "78260",
        "begin": "2020-09-14T09:30:00.000Z",
        "broadcast": "R/2020-09-14T09:30:00.000Z/P7D"
      },
      {
        "site": "dmhy",
        "id": "小松|阿松"
      },
      {
        "site": "bangumi_moe",
        "id": "560d0c9b9286e15329cf94c6"
      },
      {
        "site": "mikan",
        "id": "606"
      }
    ],
    "animeSeason": {
      "season": "FALL",
      "year": 2015,
      "month": "10"
    },
    "status": "FINISHED",
    "episodes": 25,
    "picture": "https://cdn.myanimelist.net/images/anime/7/76540.jpg",
    "thumbnail": "https://cdn.myanimelist.net/images/anime/7/76540t.jpg",
    "synonyms": [
      "Mr. Osomatsu",
      "Mr.Osomatsu",
      "Osomatsu s1",
      "Г-н Осомацу",
      "おそまつさん",
      "おそ松さん",
      "阿松"
    ]
  },
  {
    "title": "JKめし！",
    "titleTranslate": {
      "zh-Hans": [
        "女高给你做饭",
        "女高中生给你做饭了！",
        "JK食堂"
      ],
      "en": [
        "JK-Meshi",
        "JK-MESHI!"
      ]
    },
    "type": "tv",
    "lang": "ja",
    "officialSite": "http://jkmeshi.jp/",
    "begin": "2015-10-05T16:00:00.000Z",
    "end": "2016-03-28T16:05:00.000Z",
    "sites": [
      {
        "site": "bilibili",
        "id": "2767",
        "begin": "2015-10-05T16:05:00.000Z",
        "broadcast": "R/2015-10-05T16:05:00.000Z/P7D"
      },
      {
        "site": "bangumi",
        "id": "146162"
      },
      {
        "site": "dmhy",
        "id": "JK+飯|Meshi"
      },
      {
        "site": "mikan",
        "id": "604"
      }
    ],
    "animeSeason": {
      "season": "FALL",
      "year": 2015,
      "month": "10"
    },
    "status": "FINISHED",
    "episodes": 26,
    "picture": "https://cdn.myanimelist.net/images/anime/4/76261.jpg",
    "thumbnail": "https://cdn.myanimelist.net/images/anime/4/76261t.jpg",
    "synonyms": [
      "JK-MESHI!",
      "JK-Meals!",
      "JK-Meshi!",
      "JKめし!",
      "JKめし！",
      "じぇーけーめし",
      "ＪＫめし！"
    ]
  },
  {
    "title": "櫻子さんの足下には死体が埋まっている",
    "titleTranslate": {
      "zh-Hans": [
        "樱子小姐的脚下埋着尸体",
        "樱子小姐的脚下埋着秘密"
      ],
      "en": [
        "Sakurako-san no Ashimoto ni wa Shitai ga Umatteiru",
        "A Corpse Is Buried Under Sakurako's Feet"
      ]
    },
    "type": "tv",
    "lang": "ja",
    "officialSite": "http://sakurakosan.jp/",
    "begin": "2015-10-07T15:30:00.000Z",
    "end": "2015-12-23T16:00:00.000Z",
    "sites": [
      {
        "site": "bilibili",
        "id": "2742",
        "begin": "2015-10-07T17:00:00.000Z",
        "broadcast": "R/2015-10-07T17:00:00.000Z/P7D"
      },
      {
        "site": "youku",
        "id": "f4ee6f02560411e5b2ad",
        "begin": "2015-10-07T17:00:00.000Z"
      },
      {
        "site": "bangumi",
        "id": "126461"
      },
      {
        "site": "nicovideo",
        "id": "sakurakosan",
        "begin": "2015-10-28T03:00:00.000Z",
        "broadcast": "R/2015-10-28T03:00:00.000Z/P7D"
      },
      {
        "site": "unext",
        "id": "SID0020276",
        "begin": "2018-07-26T03:00:00.000Z",
        "broadcast": "R/2018-07-26T03:00:00.000Z/P7D"
      },
      {
        "site": "dmhy",
        "id": "姐+埋"
      },
      {
        "site": "bangumi_moe",
        "id": "560d0d339286e15329cf94da"
      },
      {
        "site": "mikan",
        "id": "615"
      }
    ],
    "animeSeason": {
      "season": "FALL",
      "year": 2015,
      "month": "10"
    },
    "status": "FINISHED",
    "episodes": 12,
    "picture": "https://cdn.myanimelist.net/images/anime/7/76116.jpg",
    "thumbnail": "https://cdn.myanimelist.net/images/anime/7/76116t.jpg",
    "synonyms": [
      "A Corpse Is Buried Under Sakurako`s Feet",
      "A Corpse Is Buried under Sakurako’s Feet",
      "A Corpse is Buried Under Sakurako's Feet",
      "A Corpse is Buried Under Sakurako's Feet.",
      "Beautiful Bones -Sakurako's Investigation-",
      "Beautiful Bones -Sakurako's Investigation-: Sakurako-san no Ashimoto ni wa Shitai ga Umatteiru",
      "Beautiful Bones -Sakurako’s Investigation-",
      "Beautiful Bones: Sakurako's Investigation",
      "Beautiful Bones: Sakurako`s Investigation",
      "Beautiful Bones: Sakurako’s Investigation",
      "Sakurako",
      "Sakurako-san no Ashimoto ni wa Shitai ga Umatte Iru",
      "sakurakosan",
      "Кости под ногами Сакурако",
      "Труп под ногами Сакурако",
      "Трупи під ногами Сакурако",
      "Трупът в краката на Сакурако",
      "さくらこさんのあしもとにはしたいがうまっている",
      "樱子小姐的脚下埋着尸体",
      "櫻子さんの足下には死体が埋まっている",
      "사쿠라코 씨의 발 밑에는 시체가 묻혀 있다"
    ]
  },
  {
    "title": "DD北斗の拳2 イチゴ味+",
    "titleTranslate": {
      "zh-Hans": [
        "DD北斗神拳2 草莓味+"
      ],
      "en": [
        "DD Hokuto no Ken 2: Ichigo Aji+"
      ]
    },
    "type": "tv",
    "lang": "ja",
    "officialSite": "http://www.hikanukobinukaeriminuteiounitousouhanainodaaaaa.com/",
    "begin": "2015-10-06T16:35:00.000Z",
    "end": "2015-12-22T17:05:00.000Z",
    "sites": [
      {
        "site": "youku",
        "id": "f45e2814669111e59e2a",
        "begin": "2015-10-06T17:35:00.000Z"
      },
      {
        "site": "bangumi",
        "id": "144414"
      },
      {
        "site": "nicovideo",
        "id": "ddhokuto2",
        "begin": "2015-10-11T15:00:00.000Z",
        "broadcast": "R/2015-10-11T15:00:00.000Z/P7D"
      },
      {
        "site": "unext",
        "id": "SID0020211",
        "begin": "2022-04-27T03:00:00.000Z",
        "broadcast": "R/2022-04-27T03:00:00.000Z/P7D"
      },
      {
        "site": "dmhy",
        "id": "DD北+草"
      }
    ],
    "animeSeason": {
      "season": "FALL",
      "year": 2015,
      "month": "10"
    },
    "status": "FINISHED",
    "episodes": 12,
    "picture": "https://cdn.myanimelist.net/images/anime/8/78124.jpg",
    "thumbnail": "https://cdn.myanimelist.net/images/anime/8/78124t.jpg",
    "synonyms": [
      "DD First of The North Star Ⅱ: Strawberry Flavor",
      "DD Fist of the North Star 2: Strawberry Flavor",
      "DD Fist of the North Star 2: Strawberry Flavor Plus",
      "DD Fist of the North Star 2: Strawberry Flavor+",
      "DD Fist of the North Star II",
      "DD Fist of the North Star: Strawberry Flavor",
      "DD Hokuto no Ken 2 et Hokuto no Ken: Ichigo Aji",
      "DD Hokuto no Ken 2: Ichigo Aji+",
      "DD Ken il Guerriero 2: Gusto Fragola",
      "DD北斗の拳2 イチゴ味+",
      "DD北斗の拳2 イチゴ味＋",
      "DD北斗の拳2イチゴ味+",
      "DD北斗神拳2 草莓味+",
      "Fist of the North Star: Strawberry Flavor",
      "Hokuto no Ken: Ichigo Aji",
      "でぃーでぃーほくとのけんつーいちごあじぷらす",
      "北斗の拳 イチゴ味"
    ]
  },
  {
    "title": "対魔導学園35試験小隊",
    "titleTranslate": {
      "zh-Hans": [
        "对魔导学园35试验小队",
        "対魔导学园35试験小队"
      ],
      "zh-Hant": [
        "對魔導學園35試驗小隊"
      ],
      "en": [
        "Taimadou Gakuen 35 Shiken Shoutai",
        "Anti Magic Academy The 35th Test Platoon",
        "AntiMagic Academy 35th Test Platoon"
      ]
    },
    "type": "tv",
    "lang": "ja",
    "officialSite": "http://35shoutai.jp/",
    "begin": "2015-10-07T16:05:00.000Z",
    "end": "2015-12-23T16:35:00.000Z",
    "sites": [
      {
        "site": "bilibili",
        "id": "2724",
        "begin": "2015-10-07T17:35:00.000Z",
        "broadcast": "R/2015-10-07T17:35:00.000Z/P7D"
      },
      {
        "site": "youku",
        "id": "701b312855fc11e5b5ce",
        "begin": "2015-10-07T17:35:00.000Z"
      },
      {
        "site": "bangumi",
        "id": "102140"
      },
      {
        "site": "nicovideo",
        "id": "35shoutai",
        "begin": "2015-10-24T03:00:00.000Z",
        "broadcast": "R/2015-10-24T03:00:00.000Z/P7D"
      },
      {
        "site": "iqiyi",
        "id": "a_19rrh82xr9",
        "begin": "2017-06-30T16:02:47.000Z"
      },
      {
        "site": "qq",
        "id": "d/d6kv8937dpgs0ol",
        "begin": ""
      },
      {
        "site": "ani_one_asia",
        "id": "PLxSscENEp7JgwaK0wn3LU8SGVK4mC9YSe",
        "begin": "",
        "broadcast": ""
      },
      {
        "site": "unext",
        "id": "SID0020231",
        "begin": "2015-10-24T03:00:00.000Z",
        "broadcast": "R/2015-10-24T03:00:00.000Z/P7D"
      },
      {
        "site": "dmhy",
        "id": "35+試"
      },
      {
        "site": "mikan",
        "id": "616"
      }
    ],
    "animeSeason": {
      "season": "FALL",
      "year": 2015,
      "month": "10"
    },
    "status": "FINISHED",
    "episodes": 12,
    "picture": "https://cdn.myanimelist.net/images/anime/6/76211.jpg",
    "thumbnail": "https://cdn.myanimelist.net/images/anime/6/76211t.jpg",
    "synonyms": [
      "Anti Magic Academy: Test-Trupp 35",
      "Anti Magic Academy: The 35th Test Platoon",
      "Anti-Magic Academy : The 35th Test Platoon",
      "Anti-Magic Academy Test-Trupp 35",
      "Anti-Magic Academy: Test-Trupp 35",
      "Anti-Magic Academy: The 35th Test Platoon",
      "AntiMagic Academy 35th Test Platoon",
      "AntiMagic Academy: The 35th Test Platoon",
      "Antimagic Academy 35th Test Platoon",
      "Taimadou Gakuen Sanjuugo Shiken Shoutai",
      "Taimadō Gakuen 35 Shiken Shōtai",
      "taigak",
      "Антимагическая академия: 35-е экспериментальное подразделение",
      "หมวดเตรียม 35 ล่าทรชนเวท",
      "たいまどうがくえんさんじゅうごしけんしょうたい",
      "对魔导学园35试验小队",
      "対魔導学園35試験小隊"
    ]
  },
  {
    "title": "すべてがFになる THE PERFECT INSIDER",
    "titleTranslate": {
      "zh-Hans": [
        "全部成为F",
        "全部成为F THE PERFECT INSIDER"
      ],
      "en": [
        "Subete ga F ni Naru: The Perfect Insider"
      ]
    },
    "type": "tv",
    "lang": "ja",
    "officialSite": "http://www.f-noitamina.com/",
    "begin": "2015-10-08T16:00:00.000Z",
    "end": "2015-12-17T16:35:00.000Z",
    "sites": [
      {
        "site": "bilibili",
        "id": "2726",
        "begin": "2015-10-08T17:35:00.000Z",
        "broadcast": "R/2015-10-08T17:35:00.000Z/P7D"
      },
      {
        "site": "youku",
        "id": "7d187dc855fb11e5b522",
        "begin": "2015-10-08T17:35:00.000Z"
      },
      {
        "site": "bangumi",
        "id": "118783"
      },
      {
        "site": "unext",
        "id": "SID0020215",
        "begin": "2020-11-30T03:00:00.000Z",
        "broadcast": "R/2020-11-30T03:00:00.000Z/P7D"
      },
      {
        "site": "dmhy",
        "id": "為F"
      },
      {
        "site": "bangumi_moe",
        "id": "560d0da99286e15329cf94e4"
      },
      {
        "site": "mikan",
        "id": "618"
      }
    ],
    "animeSeason": {
      "season": "FALL",
      "year": 2015,
      "month": "10"
    },
    "status": "FINISHED",
    "episodes": 11,
    "picture": "https://cdn.myanimelist.net/images/anime/9/76071.jpg",
    "thumbnail": "https://cdn.myanimelist.net/images/anime/9/76071t.jpg",
    "synonyms": [
      "Everything Becomes F: The Perfect Insider",
      "O Infiltrado Perfeito",
      "Perfecto Infiltrado",
      "Subete ga F ni Naru: THE PERFECT INSIDER",
      "Subete ga F ni Naru: The Perfect Insider",
      "The Perfect Insider",
      "The Perfect Insider: Subete ga F ni naru",
      "The Perfect Insider: Surdduee et Meurtriere - Elle est la Cle de l'Enquête",
      "subenaru",
      "Всичко се свежда до буквата F: Идеалният вътрешен човек",
      "Всё сведётся к F: Идеальный инсайдер",
      "Ключът към всичко е буквата F",
      "すべてがFになる",
      "すべてがFになる THE PERFECT INSIDER",
      "すべてがえふになるざぱーふぇくといんさいだー",
      "全部成为F",
      "모든 것이 F가 된다"
    ]
  },
  {
    "title": "不思議なソメラちゃん",
    "titleTranslate": {
      "zh-Hans": [
        "不思议美眉"
      ],
      "en": [
        "Fushigi na Somera-chan"
      ]
    },
    "type": "tv",
    "lang": "ja",
    "officialSite": "http://www.dreamcreation.co.jp/somera/",
    "begin": "2015-10-07T14:55:00.000Z",
    "end": "2015-12-23T15:00:00.000Z",
    "sites": [
      {
        "site": "bilibili",
        "id": "2733",
        "begin": "2015-10-08T15:00:00.000Z",
        "broadcast": "R/2015-10-07T15:00:00.000Z/P7D"
      },
      {
        "site": "bangumi",
        "id": "130093"
      },
      {
        "site": "nicovideo",
        "id": "somera",
        "begin": "2015-10-12T12:00:01.000Z",
        "broadcast": "R/2015-10-12T12:00:01.000Z/P7D"
      },
      {
        "site": "unext",
        "id": "SID0019778",
        "begin": "2019-01-14T03:00:00.000Z",
        "broadcast": "R/2019-01-14T03:00:00.000Z/P7D"
      },
      {
        "site": "dmhy",
        "id": "議美"
      },
      {
        "site": "bangumi_moe",
        "id": "560d0d1c9286e15329cf94d8"
      },
      {
        "site": "mikan",
        "id": "617"
      }
    ],
    "animeSeason": {
      "season": "FALL",
      "year": 2015,
      "month": "10"
    },
    "status": "FINISHED",
    "episodes": 12,
    "picture": "https://cdn.myanimelist.net/images/anime/7/76737.jpg",
    "thumbnail": "https://cdn.myanimelist.net/images/anime/7/76737t.jpg",
    "synonyms": [
      "Magical Somera Chan: Fushigi na Somera-chan",
      "Magical Somera-chan",
      "ふしぎなそめらちゃん",
      "不思議なソメラちゃん",
      "不思议美眉"
    ]
  },
  {
    "title": "ご注文はうさぎですか??",
    "titleTranslate": {
      "zh-Hans": [
        "请问您今天要来点兔子吗？？",
        "请问您今天要来点兔子吗 第二季",
        "请问您今天要来点兔子吗？ 第二季",
        "请问您点的是兔子吗？？"
      ],
      "en": [
        "Gochuumon wa Usagi Desuka 2",
        "Is the order a rabbit ??"
      ],
      "zh-Hant": [
        "請問您今天要來點兔子嗎??",
        "請問您今天要來點兔子嗎？？"
      ]
    },
    "type": "tv",
    "lang": "ja",
    "officialSite": "http://www.gochiusa.com/",
    "begin": "2015-10-10T12:30:00.000Z",
    "end": "2015-12-26T13:00:00.000Z",
    "sites": [
      {
        "site": "bilibili",
        "id": "2762",
        "begin": "2015-10-15T17:00:00.000Z",
        "broadcast": "R/2015-10-10T17:00:00.000Z/P7D"
      },
      {
        "site": "bangumi",
        "id": "123568"
      },
      {
        "site": "nicovideo",
        "id": "gochiusa2",
        "begin": "2015-10-17T03:00:00.000Z",
        "broadcast": "R/2015-10-17T03:00:00.000Z/P7D"
      },
      {
        "site": "muse_hk",
        "id": "PLuxqoToY7UchRGJOkrh2Kw0kfVtTWpn_k",
        "begin": "2021-01-31T16:00:00.000Z",
        "broadcast": "R/2021-01-31T16:00:00.000Z/P7D"
      },
      {
        "site": "abema",
        "id": "117-6zrzjibaxzh",
        "begin": "",
        "broadcast": ""
      },
      {
        "site": "unext",
        "id": "SID0019865",
        "begin": "2017-02-14T03:00:00.000Z",
        "broadcast": "R/2017-02-14T03:00:00.000Z/P7D"
      },
      {
        "site": "dmhy",
        "id": "點+兔"
      },
      {
        "site": "bangumi_moe",
        "id": "560d11dc9286e15329cf9510"
      },
      {
        "site": "mikan",
        "id": "621"
      },
      {
        "site": "gamer",
        "id": "75298",
        "begin": "2024-08-09T04:00:00.000Z",
        "broadcast": "R/2024-08-09T04:00:00.000Z/P7D"
      },
      {
        "site": "gamer_hk",
        "id": "75298",
        "begin": "2024-08-09T04:00:00.000Z",
        "broadcast": "R/2024-08-09T04:00:00.000Z/P7D"
      }
    ],
    "animeSeason": {
      "season": "FALL",
      "year": 2015,
      "month": "10"
    },
    "status": "FINISHED",
    "episodes": 12,
    "picture": "https://cdn.myanimelist.net/images/anime/8/76702.jpg",
    "thumbnail": "https://cdn.myanimelist.net/images/anime/8/76702t.jpg",
    "synonyms": [
      "GochiUsa 2",
      "Gochiusa",
      "Gochiusa 2",
      "Gochuumon wa Usagi Desu ka? 2",
      "Gochuumon wa Usagi Desu ka??",
      "Gochuumon wa Usagi Desuka 2",
      "Gochuumon wa Usagi Desuka??",
      "Gochuumon wa Usagi desu ka? 2",
      "Gochuumon wa Usagi desu ka? Season 2",
      "Gochūmon wa Usagi Desu ka? 2da temporada",
      "Gochūmon wa Usagi desu ka??",
      "Is the Order a Rabbit 2",
      "Is the Order a Rabbit??",
      "Is the Order a Rabbit?? Saison 2",
      "Is the Order a Rabbit?? Season 2",
      "Is the Order a Rabbit?? Staffel 2",
      "Is the Order a Rabbit??: Gochuumon wa Usagi Desu ka?? Temporada 2",
      "Is the order a rabbit??",
      "gochiusa s2",
      "gochiusa2",
      "ごちゅうもんはうさぎですか",
      "ご注文はうさぎですか??",
      "ご注文はうさぎですか？？",
      "请问您今天要来点兔子吗？？",
      "주문은 토끼입니까??"
    ]
  },
  {
    "title": "ヴァルキリードライヴ マーメイド",
    "titleTranslate": {
      "zh-Hans": [
        "女武神驱动",
        "女武神驱动 MERMAID",
        "女武神驱动 -美人鱼-"
      ],
      "en": [
        "Valkyrie Drive Mermaid",
        "VALKYRIE DRIVE MERMAID"
      ]
    },
    "type": "tv",
    "lang": "ja",
    "officialSite": "http://valkyriedrive.jp/anime/",
    "begin": "2015-10-10T14:30:00.000Z",
    "end": "2015-12-26T15:00:00.000Z",
    "sites": [
      {
        "site": "bangumi",
        "id": "129091"
      },
      {
        "site": "nicovideo",
        "id": "valky_ied_ive",
        "begin": "2015-10-13T15:30:00.000Z",
        "broadcast": "R/2015-10-13T15:30:00.000Z/P7D"
      },
      {
        "site": "unext",
        "id": "SID0020279",
        "begin": "2019-09-28T03:00:00.000Z",
        "broadcast": "R/2019-09-28T03:00:00.000Z/P7D"
      },
      {
        "site": "dmhy",
        "id": "Valkyrie+Drive"
      },
      {
        "site": "bangumi_moe",
        "id": "560d12029286e15329cf9512"
      },
      {
        "site": "mikan",
        "id": "623"
      }
    ],
    "animeSeason": {
      "season": "FALL",
      "year": 2015,
      "month": "10"
    },
    "status": "FINISHED",
    "episodes": 12,
    "picture": "https://cdn.myanimelist.net/images/anime/13/75528.jpg",
    "thumbnail": "https://cdn.myanimelist.net/images/anime/13/75528t.jpg",
    "synonyms": [
      "VALKYRIE DRIVE -MERMAID-",
      "Valkyrie Drive -Mermaid-",
      "Импульс Валькирии: Русалка",
      "Сила Валькирии: Русалочка",
      "ヴァルキリードライヴ マーメイド",
      "ヴァルキリードライヴ　マーメイド",
      "女武神驱动 MERMAID"
    ]
  },
  {
    "title": "モンスターストライク",
    "titleTranslate": {
      "zh-Hans": [
        "怪物弹珠"
      ],
      "en": [
        "Monster Strike"
      ]
    },
    "type": "web",
    "lang": "ja",
    "officialSite": "http://anime.monster-strike.com/",
    "begin": "2015-10-10T10:00:00.000Z",
    "end": "2016-01-02T10:30:00.000Z",
    "sites": [
      {
        "site": "mgtv",
        "id": "166526",
        "begin": ""
      },
      {
        "site": "youku",
        "id": "ef37dd98560211e5b2ad",
        "begin": "2015-10-14T12:00:00.000Z"
      },
      {
        "site": "bangumi",
        "id": "133608"
      },
      {
        "site": "dmhy",
        "id": "Monster+Strike"
      },
      {
        "site": "mikan",
        "id": "624"
      }
    ],
    "animeSeason": {
      "season": "SUMMER",
      "year": 2018,
      "month": "10"
    },
    "status": "FINISHED",
    "episodes": 63,
    "picture": "https://cdn.myanimelist.net/images/anime/1415/101689.jpg",
    "thumbnail": "https://cdn.myanimelist.net/images/anime/1415/101689t.jpg",
    "synonyms": [
      "Anime Monster Strike",
      "Monster Strike Season 4",
      "Monster Strike the Animation",
      "アニメ モンスターストライク",
      "モンスターストライク",
      "モンスターストライク The Animation",
      "モンストアニメ"
    ]
  },
  {
    "title": "牙狼 -紅蓮ノ月-",
    "titleTranslate": {
      "zh-Hans": [
        "牙狼 红莲之月"
      ],
      "en": [
        "Garo: Guren no Tsuki"
      ]
    },
    "type": "tv",
    "lang": "ja",
    "officialSite": "http://garo-project.jp/ANIME2/",
    "begin": "2015-10-09T16:23:00.000Z",
    "end": "2016-04-01T16:53:00.000Z",
    "sites": [
      {
        "site": "bilibili",
        "id": "2774",
        "begin": "2015-10-09T17:30:00.000Z",
        "broadcast": "R/2015-10-09T17:30:00.000Z/P7D"
      },
      {
        "site": "youku",
        "id": "0ba98662579c11e5a080",
        "begin": "2015-10-09T17:30:00.000Z"
      },
      {
        "site": "iqiyi",
        "id": "a_19rrhbb219",
        "begin": "2015-10-09T17:30:00.000Z"
      },
      {
        "site": "bangumi",
        "id": "141078"
      },
      {
        "site": "nicovideo",
        "id": "garo-project2",
        "begin": "2015-10-16T15:30:00.000Z",
        "broadcast": "R/2015-10-16T15:30:00.000Z/P7D"
      },
      {
        "site": "unext",
        "id": "SID0020391",
        "begin": "2020-05-02T03:00:00.000Z",
        "broadcast": "R/2020-05-02T03:00:00.000Z/P7D"
      },
      {
        "site": "dmhy",
        "id": "牙+之月|Moon"
      },
      {
        "site": "bangumi_moe",
        "id": "560d0f529286e15329cf94f4"
      },
      {
        "site": "mikan",
        "id": "619"
      }
    ],
    "animeSeason": {
      "season": "FALL",
      "year": 2015,
      "month": "10"
    },
    "status": "FINISHED",
    "episodes": 23,
    "picture": "https://cdn.myanimelist.net/images/anime/2/76029.jpg",
    "thumbnail": "https://cdn.myanimelist.net/images/anime/2/76029t.jpg",
    "synonyms": [
      "GARO 紅蓮ノ月",
      "GARO: CRIMSON MOON",
      "GARO: Guren no Tsuki",
      "Garo 2nd Season",
      "Garo: Crimson Moon",
      "Garo: The Crimson Moon",
      "Гаро: Багровая луна",
      "牙狼 -紅蓮ノ月-",
      "牙狼 红莲之月",
      "牙狼[GARO]-紅蓮ノ月-",
      "牙狼〈GARO〉-紅蓮ノ月-"
    ]
  },
  {
    "title": "どうしても干支にはいりたい",
    "titleTranslate": {
      "zh-Hans": [
        "无论如何都想加入生肖"
      ]
    },
    "type": "tv",
    "lang": "ja",
    "officialSite": "http://etononeko.jp/",
    "begin": "2015-10-11T00:20:00.000Z",
    "end": "2016-01-10T00:30:00.000Z",
    "sites": [
      {
        "site": "bangumi",
        "id": "145912"
      },
      {
        "site": "acfun",
        "id": "5020100",
        "begin": "2017-11-13T09:28:19.000Z"
      }
    ],
    "animeSeason": {
      "season": "FALL",
      "year": 2015,
      "month": "10"
    },
    "status": "FINISHED",
    "episodes": 13,
    "picture": "https://cdn.myanimelist.net/images/anime/2/88675.jpg",
    "thumbnail": "https://cdn.myanimelist.net/images/anime/2/88675t.jpg",
    "synonyms": [
      "Dōshitemo Eto ni Hairitai",
      "Etoneko",
      "I Really Want to Join the Zodiac",
      "No Matter What I Want to Join the Zodiac",
      "どうしても干支にはいりたい",
      "无论如何都想加入生肖"
    ]
  },
  {
    "title": "ブレイブビーツ",
    "titleTranslate": {
      "zh-Hans": [
        "勇敢节奏"
      ],
      "en": [
        "Brave Beats",
        "brave beats"
      ]
    },
    "type": "tv",
    "lang": "ja",
    "officialSite": "http://www.bravebeats.net/",
    "begin": "2015-10-10T22:00:00.000Z",
    "end": "2016-03-26T22:30:00.000Z",
    "sites": [
      {
        "site": "bangumi",
        "id": "146402"
      }
    ],
    "animeSeason": {
      "season": "FALL",
      "year": 2015,
      "month": "10"
    },
    "status": "FINISHED",
    "episodes": 22,
    "picture": "https://cdn.myanimelist.net/images/anime/3/76152.jpg",
    "thumbnail": "https://cdn.myanimelist.net/images/anime/3/76152t.jpg",
    "synonyms": [
      "ぶれいぶびーつ",
      "ブレイブビーツ"
    ]
  },
  {
    "title": "カードファイト!! ヴァンガードG ギアースクライシス編",
    "titleTranslate": {
      "zh-Hans": [
        "卡片战斗先导者G 齿轮危机篇"
      ],
      "en": [
        "CARDFIGHT!! Vanguard G GEARS CRISIS"
      ]
    },
    "type": "tv",
    "lang": "ja",
    "officialSite": "http://www.tv-tokyo.co.jp/anime/cf-vanguard-g2/",
    "begin": "2015-10-11T01:00:00.000Z",
    "end": "2016-04-10T01:30:00.000Z",
    "sites": [
      {
        "site": "bangumi",
        "id": "146404"
      },
      {
        "site": "unext",
        "id": "SID0058897",
        "begin": "2021-06-22T03:00:00.000Z",
        "broadcast": "R/2021-06-22T03:00:00.000Z/P7D"
      }
    ],
    "animeSeason": {
      "season": "FALL",
      "year": 2015,
      "month": "10"
    },
    "status": "FINISHED",
    "episodes": 26,
    "picture": "https://cdn.myanimelist.net/images/anime/3/76231.jpg",
    "thumbnail": "https://cdn.myanimelist.net/images/anime/3/76231t.jpg",
    "synonyms": [
      "CARDFIGHT!! ヴァンガードG ギアースクライシス編",
      "Cardfight!! Vanguard G GIRS Crisis",
      "Cardfight!! Vanguard G: GIRS Crisis",
      "Cardfight!! Vanguard G: GIRS Crisis Arc",
      "Cardfight!! Vanguard G: Gears Crisis Hen",
      "Cardfight!! Vanguard G: Gears Crisis-hen",
      "Cardfight!! Vanguard G: Girs Crisis Hen",
      "カードファイト!! ヴァンガードG ギアースクライシス編",
      "カードファイト!! ヴァンガードG　ギアースクライシス編",
      "卡片战斗先导者G 齿轮危机篇"
    ]
  },
  {
    "title": "あにトレ！EX",
    "titleTranslate": {
      "zh-Hans": [
        "动画锻炼！EX"
      ],
      "en": [
        "Anitore EX",
        "anime de training"
      ]
    },
    "type": "tv",
    "lang": "ja",
    "officialSite": "http://anime-training.com/",
    "begin": "2015-10-12T16:11:00.000Z",
    "end": "2015-12-28T16:16:00.000Z",
    "sites": [
      {
        "site": "mgtv",
        "id": "292433",
        "begin": ""
      },
      {
        "site": "youku",
        "id": "a5fd9966560611e5b522",
        "begin": "2015-10-12T19:00:00.000Z"
      },
      {
        "site": "bangumi",
        "id": "145129"
      },
      {
        "site": "nicovideo",
        "id": "ch2614797",
        "begin": "",
        "broadcast": ""
      },
      {
        "site": "unext",
        "id": "SID0020094",
        "begin": "2015-10-13T03:00:00.000Z",
        "broadcast": "R/2015-10-13T03:00:00.000Z/P7D"
      },
      {
        "site": "dmhy",
        "id": "鍛|ANITORE|training+EX"
      },
      {
        "site": "bangumi_moe",
        "id": "560d0cba9286e15329cf94ca"
      },
      {
        "site": "mikan",
        "id": "629"
      }
    ],
    "animeSeason": {
      "season": "FALL",
      "year": 2015,
      "month": "10"
    },
    "status": "FINISHED",
    "episodes": 12,
    "picture": "https://cdn.myanimelist.net/images/anime/3/77048.jpg",
    "thumbnail": "https://cdn.myanimelist.net/images/anime/3/77048t.jpg",
    "synonyms": [
      "Ani Tore! EX",
      "Anime De Training! EX",
      "Anime De Training! Ex",
      "Anime de Training EX",
      "Anime de Training! EX",
      "Anime de Training! Ex",
      "Аниме-тренировки",
      "あにトレ! EX",
      "あにトレ!EX",
      "あにトレ！ EX",
      "あにトレ！EX",
      "あにトレ！ＥＸ",
      "动画锻炼！EX"
    ]
  },
  {
    "title": "血液型くん！3",
    "titleTranslate": {
      "zh-Hans": [
        "血型君3",
        "血型君 第三季"
      ],
      "en": [
        "Ketsuekigata-kun 3"
      ]
    },
    "type": "tv",
    "lang": "ja",
    "officialSite": "http://ketsuekigatakun.com/",
    "begin": "2015-10-12T16:08:00.000Z",
    "end": "2015-12-28T16:11:00.000Z",
    "sites": [
      {
        "site": "bangumi",
        "id": "145667"
      },
      {
        "site": "nicovideo",
        "id": "ch2614799",
        "begin": "",
        "broadcast": ""
      },
      {
        "site": "dmhy",
        "id": "血+型"
      },
      {
        "site": "bangumi_moe",
        "id": "560d0cc99286e15329cf94cc"
      },
      {
        "site": "mikan",
        "id": "628"
      }
    ],
    "animeSeason": {
      "season": "FALL",
      "year": 2015,
      "month": "10"
    },
    "status": "FINISHED",
    "episodes": 12,
    "picture": "https://cdn.myanimelist.net/images/anime/12/76703.jpg",
    "thumbnail": "https://cdn.myanimelist.net/images/anime/12/76703t.jpg",
    "synonyms": [
      "Ketsuekigata-kun! 3rd Season",
      "けつえきがたくんすりー",
      "血型君3",
      "血液型くん! 3",
      "血液型くん！ 3",
      "血液型くん！3",
      "血液型くん！３"
    ]
  },
  {
    "title": "どちゃもん じゅにあ",
    "titleTranslate": {},
    "type": "tv",
    "lang": "ja",
    "officialSite": "http://www9.nhk.or.jp/anime/dochamon/",
    "begin": "2015-10-05T09:45:00.000Z",
    "end": "2016-02-22T09:55:00.000Z",
    "sites": [
      {
        "site": "bangumi",
        "id": "209643"
      }
    ],
    "animeSeason": {
      "season": "FALL",
      "year": 2015,
      "month": "10"
    },
    "status": "FINISHED",
    "episodes": 16,
    "picture": "https://cdn.myanimelist.net/images/anime/9/76520.jpg",
    "thumbnail": "https://cdn.myanimelist.net/images/anime/9/76520t.jpg",
    "synonyms": [
      "どちゃもん じゅにあ",
      "どちゃもんじゅにあ"
    ]
  },
  {
    "title": "猫なんかよんでもこない。",
    "titleTranslate": {
      "zh-Hans": [
        "为什么猫都叫不来"
      ]
    },
    "type": "tv",
    "lang": "ja",
    "officialSite": "http://www.tv-osaka.co.jp/nekoyon/",
    "begin": "2015-10-02T15:54:00.000Z",
    "end": "2015-12-18T16:00:00.000Z",
    "sites": [
      {
        "site": "bangumi",
        "id": "148072"
      },
      {
        "site": "bilibili",
        "id": "4106",
        "begin": "2015-10-01T16:00:01.000Z",
        "broadcast": "R/2016-05-27T03:27:00.000Z/P7D"
      }
    ],
    "animeSeason": {
      "season": "FALL",
      "year": 2015,
      "month": "10"
    },
    "status": "FINISHED",
    "episodes": 12,
    "picture": "https://cdn.myanimelist.net/images/anime/2/76535.jpg",
    "thumbnail": "https://cdn.myanimelist.net/images/anime/2/76535t.jpg",
    "synonyms": [
      "Cats Don't Come When You Call Them.",
      "Neko Nanka Yonde mo Konai",
      "Neko Nanka Yonde mo Konai.",
      "Neko Nanka Yondemo Konai.",
      "Neko nanka Yonde mo Konai.",
      "NekoYon",
      "ねこなんかよんでもこない",
      "猫なんかよんでもこない.",
      "猫なんかよんでもこない。"
    ]
  },
  {
    "title": "劇場版 蒼き鋼のアルペジオ -アルス・ノヴァ- Cadenza",
    "titleTranslate": {
      "zh-Hans": [
        "苍蓝钢铁的琶音 Cadenza"
      ]
    },
    "type": "movie",
    "lang": "ja",
    "officialSite": "http://www.aokihagane.com/",
    "begin": "2015-10-03T16:00:00.000Z",
    "end": "2015-10-03T17:30:00.000Z",
    "sites": [
      {
        "site": "bangumi",
        "id": "107100"
      },
      {
        "site": "unext",
        "id": "SID0027854",
        "begin": "2017-01-05T03:00:00.000Z",
        "broadcast": "R/2017-01-05T03:00:00.000Z/P7D"
      },
      {
        "site": "mikan",
        "id": "806"
      }
    ],
    "animeSeason": {
      "season": "FALL",
      "year": 2015,
      "month": "10"
    },
    "status": "FINISHED",
    "episodes": 1,
    "picture": "https://cdn.myanimelist.net/images/anime/2/74665.jpg",
    "thumbnail": "https://cdn.myanimelist.net/images/anime/2/74665t.jpg",
    "synonyms": [
      "Aoki Hagane no Arpeggio: Ars Nova - Cadenza",
      "Aoki Hagane no Arpeggio: Ars Nova Cadenza",
      "Aoki Hagane no Arpeggio: Ars Nova Movie 2",
      "Arpeggio of Blue Steel - Cadenza",
      "Arpeggio of Blue Steel Movie 2: Ars Nova - Cadenza",
      "Arpeggio of Blue Steel: Ars Nova Cadenza",
      "Arpeggio of Blue Steel: Ars Nova Movie 2",
      "Gekijouban Aoki Hagane no Arpeggio",
      "劇場版 蒼き鋼のアルペジオ -アルス・ノヴァ- Cadenza",
      "劇場版 蒼き鋼のアルペジオ ‐アルス・ノヴァ‐ Cadenza"
    ]
  },
  {
    "title": "屍者の帝国",
    "titleTranslate": {
      "zh-Hans": [
        "尸者的帝国"
      ]
    },
    "type": "movie",
    "lang": "ja",
    "officialSite": "http://project-itoh.com/",
    "begin": "2015-10-02T16:00:00.000Z",
    "end": "2015-10-02T18:00:00.000Z",
    "sites": [
      {
        "site": "bangumi",
        "id": "118784"
      },
      {
        "site": "bilibili",
        "id": "4098",
        "begin": "2015-10-01T16:00:01.000Z",
        "broadcast": "R/2016-05-27T02:53:05.000Z/P7D"
      }
    ],
    "animeSeason": {
      "season": "FALL",
      "year": 2015,
      "month": "10"
    },
    "status": "FINISHED",
    "episodes": 1,
    "picture": "https://cdn.myanimelist.net/images/anime/4/75468.jpg",
    "thumbnail": "https://cdn.myanimelist.net/images/anime/4/75468t.jpg",
    "synonyms": [
      "El Imperio de los Cadáveres",
      "El imperio de los cadáveres",
      "L'Impero dei Cadaveri",
      "L`impero dei cadaveri",
      "Project Itoh",
      "Project Itoh: The Empire of Corpses",
      "The Empire of Corpses",
      "Империя мертвецов",
      "Империя мертвых",
      "Империя мёртвых",
      "Империя трупов",
      "ししゃのていこく",
      "尸者的帝国",
      "屍者の帝国",
      "屍者の帝国 The Empire of Corpses",
      "屍者的帝國"
    ]
  },
  {
    "title": "創勢のアクエリオンEVOL",
    "titleTranslate": {
      "zh-Hans": [
        "创势的大天使EVOL"
      ]
    },
    "type": "ova",
    "lang": "ja",
    "officialSite": "",
    "begin": "2015-10-28T16:00:00.000Z",
    "end": "2015-10-28T16:30:00.000Z",
    "sites": [
      {
        "site": "bangumi",
        "id": "129131"
      }
    ],
    "animeSeason": {
      "season": "SUMMER",
      "year": 2015,
      "month": "10"
    },
    "status": "FINISHED",
    "episodes": 1,
    "picture": "https://cdn.myanimelist.net/images/anime/8/72733.jpg",
    "thumbnail": "https://cdn.myanimelist.net/images/anime/8/72733t.jpg",
    "synonyms": [
      "Aquarion Love",
      "Genesis of Aquarion EVOL",
      "Genesis of Aquarion Evol",
      "Genesis of Aquarion Love",
      "Sousei no Aquarion EVOL",
      "Sousei no Aquarion Love",
      "Sōsei no Aquarion Evol",
      "创势的大天使EVOL",
      "創勢のアクエリオンEVOL",
      "創勢のアクエリオンEvol"
    ]
  },
  {
    "title": "ビッグオーダー OAD",
    "titleTranslate": {
      "zh-Hans": [
        "至高指令 OAD"
      ]
    },
    "type": "ova",
    "lang": "ja",
    "officialSite": "http://www.asread.net/bo.html",
    "begin": "2015-10-03T16:00:00.000Z",
    "end": "2015-10-03T16:00:00.000Z",
    "sites": [
      {
        "site": "bangumi",
        "id": "126157"
      }
    ],
    "animeSeason": {
      "season": "FALL",
      "year": 2015,
      "month": "10"
    },
    "status": "FINISHED",
    "episodes": 1,
    "picture": "https://cdn.myanimelist.net/images/anime/12/78945.jpg",
    "thumbnail": "https://cdn.myanimelist.net/images/anime/12/78945t.jpg",
    "synonyms": [
      "BIG ORDER OVA",
      "Big Order (OVA)",
      "Big Order OVA",
      "びっぐおーだー",
      "ビッグオーダー",
      "ビッグオーダー OAD",
      "至高指令"
    ]
  },
  {
    "title": "猫のダヤン　日本へ行く",
    "titleTranslate": {
      "zh-Hant": [
        "達洋貓：穿越時空的奪色冒險",
        "達洋貓S2 ：穿越時空的奪色冒險",
        "達洋貓第二季"
      ]
    },
    "type": "tv",
    "lang": "ja",
    "officialSite": "http://anime-dayan.com/",
    "begin": "2015-10-17T16:00:00.000Z",
    "end": "2016-01-09T16:30:00.000Z",
    "sites": [
      {
        "site": "bangumi",
        "id": "258329"
      },
      {
        "site": "iqiyi",
        "id": "a_19rrh5n9sd",
        "begin": "2018-08-24T09:59:15.000Z"
      },
      {
        "site": "muse_hk",
        "id": "PLuxqoToY7Uch2nFpGgRSQvgcTHojOsjH3",
        "begin": "2019-06-10T16:00:00.000Z",
        "broadcast": "R/2019-06-10T16:00:00.000Z/P7D",
        "comment": "中文:PLuxqoToY7Uch8tzidPoE3nhhBUFDptjEF"
      },
      {
        "site": "unext",
        "id": "SID0028313",
        "begin": "2021-01-31T03:00:00.000Z",
        "broadcast": "R/2021-01-31T03:00:00.000Z/P7D"
      }
    ],
    "animeSeason": {
      "season": "FALL",
      "year": 2015,
      "month": "10"
    },
    "status": "FINISHED",
    "episodes": 12,
    "picture": "https://cdn.myanimelist.net/images/anime/2/76100.jpg",
    "thumbnail": "https://cdn.myanimelist.net/images/anime/2/76100t.jpg",
    "synonyms": [
      "Dayan the Cat 2",
      "Dayan the Cat Goes to Japan",
      "Neko no Dayan 2",
      "Neko no Dayan, Nihon e Iku",
      "猫のダヤン 日本へ行く",
      "猫のダヤン　日本へ行く",
      "猫のダヤン日本へ行く"
    ]
  },
  {
    "title": "RWBY Volume 3",
    "titleTranslate": {
      "zh-Hans": [
        "红白黑黄 第三季",
        "四色战记 / RWBY 第三季"
      ]
    },
    "type": "web",
    "lang": "en",
    "officialSite": "http://roosterteeth.com/home.php",
    "begin": "2015-10-24T16:00:00.000Z",
    "end": "2016-02-13T16:30:00.000Z",
    "comment": "",
    "sites": [
      {
        "site": "bangumi",
        "id": "138180"
      },
      {
        "site": "bilibili",
        "id": "28236841",
        "begin": "2022-02-06T10:00:01.000Z",
        "broadcast": "R/2022-02-06T10:00:01.000Z/P7D"
      },
      {
        "site": "bangumi_moe",
        "id": "565c98fd3a0b6c55038cb858"
      }
    ],
    "animeSeason": {
      "season": "FALL",
      "year": 2015,
      "month": "10"
    },
    "status": "FINISHED",
    "episodes": 12,
    "picture": "https://media.kitsu.app/anime/poster_images/11117/small.jpg",
    "thumbnail": "https://media.kitsu.app/anime/poster_images/11117/tiny.jpg",
    "synonyms": [
      "RWBY Season 3",
      "RWBY Volume 3"
    ]
  },
  {
    "title": "長門有希ちゃんの消失 OAD",
    "titleTranslate": {
      "zh-Hans": [
        "长门有希酱的消失 OAD"
      ]
    },
    "type": "ova",
    "lang": "ja",
    "officialSite": "",
    "begin": "2015-10-26T16:00:00.000Z",
    "end": "2015-10-26T16:00:00.000Z",
    "comment": "",
    "sites": [
      {
        "site": "bangumi",
        "id": "129960"
      },
      {
        "site": "bilibili",
        "id": "6407",
        "begin": "2015-10-25T16:00:00.000Z",
        "broadcast": "R/2017-08-29T16:00:00.000Z/P7D"
      }
    ],
    "animeSeason": {
      "season": "FALL",
      "year": 2015,
      "month": "10"
    },
    "status": "FINISHED",
    "episodes": 1,
    "picture": "https://cdn.myanimelist.net/images/anime/6/76840.jpg",
    "thumbnail": "https://cdn.myanimelist.net/images/anime/6/76840t.jpg",
    "synonyms": [
      "Das Verscheinden der Yuki Nagato: OVA Endlosen Sommerferien",
      "Das Verschwinden der Yuki Nagato OVA",
      "Das Verschwinden der Yuki Nagato: Endlose Sommerferien",
      "La disparition de Yuki Nagato : Vacances d’été sans fin",
      "Nagato Yuki-chan no Shoushitsu OAD",
      "Nagato Yuki-chan no Shoushitsu OVA",
      "Nagato Yuki-chan no Shōshitsu: Owarenai Natsuyasumi",
      "The Disappearance of Nagato Yuki-Chan",
      "The Disappearance of Nagato Yuki-Chan OAD",
      "The Disappearance of Nagato Yuki-Chan: I Cannot Let Summer Break End",
      "The Disappearance of Nagato Yuki-chan OVA",
      "The Disappearance of Nagato Yuki-chan: I Cannot Let Summer Break End",
      "The Vanishing of Nagato Yuki-chan OVA",
      "haruhi ova",
      "nagatoyuki ova",
      "nagatoyukichan ova",
      "長門有希ちゃんの消失 OAD",
      "長門有希ちゃんの消失 第17話「終われない夏休み」",
      "長門有希ちゃんの消失 終われない夏休み",
      "長門有希ちゃんの消失「終われない夏休み」",
      "长门有希的消失 无法结束的暑假",
      "나가토 유키짱의 소실: 끝낼 수 없는 여름방학"
    ]
  },
  {
    "title": "カレバカ～吾輩ノ彼ハ馬鹿でR～",
    "titleTranslate": {
      "zh-Hans": [
        "笨蛋男友"
      ]
    },
    "type": "web",
    "lang": "ja",
    "officialSite": "http://www.younganimal-densi.com/karebaka_anime",
    "begin": "2015-10-16T16:00:00.000Z",
    "end": "2016-01-22T16:30:00.000Z",
    "comment": "",
    "sites": [
      {
        "site": "bangumi",
        "id": "132836"
      },
      {
        "site": "bilibili",
        "id": "4083",
        "begin": "2015-10-15T16:00:00.000Z",
        "broadcast": "R/2016-05-26T09:49:00.000Z/P7D"
      }
    ],
    "animeSeason": {
      "season": "FALL",
      "year": 2015,
      "month": "10"
    },
    "status": "FINISHED",
    "episodes": 8,
    "picture": "https://cdn.myanimelist.net/images/anime/2/76734.jpg",
    "thumbnail": "https://cdn.myanimelist.net/images/anime/2/76734t.jpg",
    "synonyms": [
      "Idiot Boyfriend: My Boyfriend is an Idiot",
      "Kare Baka - Wagahai no Kare wa Baka de R",
      "Kare Baka: Wagahai no Kare wa Baka de Aru",
      "カレバカ 吾輩ノ彼ハ馬鹿である",
      "カレバカ~吾輩ノ彼ハ馬鹿でR~",
      "カレバカ～吾輩ノ彼ハ馬鹿でR～"
    ]
  },
  {
    "title": "きょーふ！ゾンビ猫",
    "titleTranslate": {
      "zh-Hans": [
        "恐怖！僵尸猫"
      ]
    },
    "type": "tv",
    "lang": "ja",
    "officialSite": "",
    "begin": "2015-10-01T16:00:00.000Z",
    "end": "2016-09-29T16:30:00.000Z",
    "comment": "",
    "sites": [
      {
        "site": "bangumi",
        "id": "145734"
      },
      {
        "site": "bilibili",
        "id": "2990",
        "begin": "2015-09-30T16:00:00.000Z",
        "broadcast": "R/2015-11-12T17:05:00.000Z/P7D"
      },
      {
        "site": "unext",
        "id": "SID0025112",
        "begin": "2020-12-11T03:00:00.000Z",
        "broadcast": "R/2020-12-11T03:00:00.000Z/P7D"
      }
    ],
    "animeSeason": {
      "season": "FALL",
      "year": 2015,
      "month": "10"
    },
    "status": "FINISHED",
    "episodes": 52,
    "picture": "https://cdn.myanimelist.net/images/anime/13/76568.jpg",
    "thumbnail": "https://cdn.myanimelist.net/images/anime/13/76568t.jpg",
    "synonyms": [
      "Kyoufu! Zombie Cat",
      "Kyōfu! Zombie Neko",
      "きょーふ! ゾンビ猫",
      "きょーふ！ ゾンビ猫",
      "きょーふ！ゾンビ猫"
    ]
  }
]