[
  {
    "title": "超獣機神ダンクーガ",
    "titleTranslate": {
      "zh-Hans": [
        "超兽机神断空我"
      ]
    },
    "type": "tv",
    "lang": "ja",
    "officialSite": "",
    "begin": "1985-04-05T10:00:00.000Z",
    "end": "1985-12-27T10:55:00.000Z",
    "sites": [
      {
        "site": "bangumi",
        "id": "20831"
      },
      {
        "site": "unext",
        "id": "SID0004809",
        "begin": "2016-03-24T03:00:00.000Z",
        "broadcast": "R/2016-03-24T03:00:00.000Z/P7D"
      }
    ],
    "animeSeason": {
      "season": "SPRING",
      "year": 1985,
      "month": "04"
    },
    "status": "FINISHED",
    "episodes": 38,
    "picture": "https://u.livechart.me/anime/6712/poster_image/a8f4666b90fdbb961b45daff8f8cc61a.jpg/large.jpg",
    "thumbnail": "https://u.livechart.me/anime/6712/poster_image/a8f4666b90fdbb961b45daff8f8cc61a.jpg/small.jpg",
    "synonyms": [
      "Chōjū Kishin Dancōgar",
      "Dancouga",
      "Dancouga: Super Beast Machine God",
      "Dancougar",
      "Dancougar - Super Beast Machine God",
      "Dancougar, les cadets de l`espace",
      "God Bless The Machine Dancougar",
      "Super Beastial Machine God Dancougar",
      "Super Bestial Machine God Dancougar",
      "Super Mechanimal Dancougar",
      "ちょうじゅうきしんだんくーが",
      "ダンクーガ",
      "超獣機神ダンクーガ"
    ]
  },
  {
    "title": "おねがい！サミアどん",
    "titleTranslate": {
      "en": [
        "Onegai! Samia Don",
        "Please! Psammea-don, Sablotin"
      ]
    },
    "type": "tv",
    "lang": "ja",
    "officialSite": "",
    "begin": "1985-04-02T22:30:00.000Z",
    "end": "1986-02-04T23:00:00.000Z",
    "sites": [
      {
        "site": "bangumi",
        "id": "213634"
      },
      {
        "site": "unext",
        "id": "SID0038640",
        "begin": "2019-01-10T03:00:00.000Z",
        "broadcast": "R/2019-01-10T03:00:00.000Z/P7D"
      }
    ],
    "animeSeason": {
      "season": "SPRING",
      "year": 1985,
      "month": "04"
    },
    "status": "FINISHED",
    "episodes": 39,
    "picture": "https://u.livechart.me/anime/9170/poster_image/cc99585ebc98176a9a0e0380439f7c6d.jpg/large.jpg",
    "thumbnail": "https://u.livechart.me/anime/9170/poster_image/cc99585ebc98176a9a0e0380439f7c6d.jpg/small.jpg",
    "synonyms": [
      "Five Children and It (1985)",
      "Please! Psammea-don",
      "Psammed, il folletto della sabbia",
      "Sablotin",
      "Samed",
      "Samed, el Duende Mágico",
      "The Psammead",
      "el Duende Magico",
      "سميد",
      "おねがい! サミアどん",
      "おねがいさみあどん",
      "おねがい！サミアどん",
      "모래요정 바람돌이"
    ]
  },
  {
    "title": "プロゴルファー猿",
    "titleTranslate": {
      "zh-Hans": [
        "球场小神将",
        "职业高尔夫猿"
      ]
    },
    "type": "tv",
    "lang": "ja",
    "officialSite": "",
    "begin": "1985-04-01T16:00:00.000Z",
    "broadcast": "R/1985-04-01T16:00:00.000Z/P7D",
    "end": "1988-03-27T16:00:00.000Z",
    "comment": "",
    "sites": [
      {
        "site": "bangumi",
        "id": "189441"
      },
      {
        "site": "unext",
        "id": "SID0004803",
        "begin": "2016-02-18T15:00:00.000Z",
        "broadcast": "R/2016-02-18T15:00:00.000Z/P7D"
      },
      {
        "site": "abema",
        "id": "35-5dpiptebuab",
        "begin": "",
        "broadcast": ""
      }
    ],
    "animeSeason": {
      "season": "SPRING",
      "year": 1985,
      "month": "04"
    },
    "status": "FINISHED",
    "episodes": 143,
    "picture": "https://u.livechart.me/anime/12213/poster_image/5dad8f05729c28c8e58ba678bfafd25b.webp/large.jpg",
    "thumbnail": "https://u.livechart.me/anime/12213/poster_image/5dad8f05729c28c8e58ba678bfafd25b.webp/small.jpg",
    "synonyms": [
      "Pro Golfer Saru (1985)",
      "Pro Golfer Saru TV",
      "pgs",
      "プロゴルファー猿",
      "プロゴルファー猿 (1985)",
      "プロゴルファー猿 （1985）",
      "球场小神将（1985）"
    ]
  },
  {
    "title": "タッチ",
    "titleTranslate": {
      "zh-Hans": [
        "棒球英豪",
        "棒球英豪 TV版"
      ]
    },
    "type": "tv",
    "lang": "ja",
    "officialSite": "http://www.kbs-kyoto.co.jp/tv/anime/touch/",
    "begin": "1985-03-24T22:30:00.000Z",
    "end": "1987-03-22T23:00:00.000Z",
    "sites": [
      {
        "site": "qq",
        "id": "m/m2oobmidz797a2w",
        "begin": ""
      },
      {
        "site": "bangumi",
        "id": "2741"
      },
      {
        "site": "bilibili",
        "id": "2425",
        "begin": "2013-03-20T13:52:00.000Z",
        "broadcast": "R/2013-03-20T13:52:00.000Z/P7D"
      },
      {
        "site": "unext",
        "id": "SID0040172",
        "begin": "2019-03-31T03:00:00.000Z",
        "broadcast": "R/2019-03-31T03:00:00.000Z/P7D"
      }
    ],
    "animeSeason": {
      "season": "SPRING",
      "year": 1985,
      "month": "03"
    },
    "status": "FINISHED",
    "episodes": 101,
    "picture": "https://u.livechart.me/anime/5920/poster_image/41d91c474b618f24b8946dc82786a834.jpg/large.jpg",
    "thumbnail": "https://u.livechart.me/anime/5920/poster_image/41d91c474b618f24b8946dc82786a834.jpg/small.jpg",
    "synonyms": [
      "Bateadores",
      "Prendi il mondo e vai",
      "Théo ou la Batte de la Victoire",
      "Théo ou la batte de la victoire",
      "Touch TV",
      "Touch: Bateadores",
      "Касание",
      "لمسة",
      "ทัช ยอดรักนักกีฬา",
      "たっち",
      "タッチ",
      "棒球英豪",
      "터치"
    ]
  },
  {
    "title": "機動戦士Zガンダム",
    "titleTranslate": {
      "zh-Hans": [
        "机动战士Z高达"
      ]
    },
    "type": "tv",
    "lang": "ja",
    "officialSite": "http://www.z-gundam.net/",
    "begin": "1985-03-02T15:30:00.000Z",
    "end": "1986-02-22T16:00:00.000Z",
    "sites": [
      {
        "site": "qq",
        "id": "7/7z6r2ttxucgry3j",
        "begin": ""
      },
      {
        "site": "bangumi",
        "id": "9622"
      },
      {
        "site": "unext",
        "id": "SID0012900",
        "begin": "2010-04-30T15:00:00.000Z",
        "broadcast": "R/2010-04-30T15:00:00.000Z/P7D"
      }
    ],
    "animeSeason": {
      "season": "SPRING",
      "year": 1985,
      "month": "03"
    },
    "status": "FINISHED",
    "episodes": 50,
    "picture": "https://u.livechart.me/anime/4659/poster_image/9d79504831291430e79338d62079356b.webp/large.jpg",
    "thumbnail": "https://u.livechart.me/anime/4659/poster_image/9d79504831291430e79338d62079356b.webp/small.jpg",
    "synonyms": [
      "Gundam Z",
      "Gundam: Kidou Senshi Z Gundam",
      "Kidou Senshi Z Gundam",
      "Kidou Senshi Zeta Gundam",
      "Kidō Senshi Z Gundam",
      "Mobile Suit Z Gundam",
      "Z Gundam",
      "Zeta Gundam",
      "机动战士Z高达",
      "機動戦士Zガンダム",
      "機動戦士Ζガンダム"
    ]
  },
  {
    "title": "ドラえもん のび太の宇宙小戦争",
    "titleTranslate": {
      "zh-Hans": [
        "哆啦A梦：大雄的宇宙小战争"
      ]
    },
    "type": "movie",
    "lang": "ja",
    "officialSite": "",
    "begin": "1985-03-16T16:00:00.000Z",
    "end": "1985-03-16T17:30:00.000Z",
    "sites": [
      {
        "site": "bangumi",
        "id": "441"
      },
      {
        "site": "qq",
        "id": "z/z8alyhrvkd3jp2y",
        "begin": ""
      },
      {
        "site": "bilibili",
        "id": "2553",
        "begin": "1985-03-15T16:00:00.000Z",
        "broadcast": "R/2015-02-28T06:01:17.000Z/P7D"
      },
      {
        "site": "abema",
        "id": "35-46",
        "begin": "",
        "broadcast": ""
      },
      {
        "site": "unext",
        "id": "SID0099849",
        "begin": "2024-03-05T03:00:00.000Z",
        "broadcast": "R/2024-03-05T03:00:00.000Z/P7D"
      }
    ],
    "animeSeason": {
      "season": "SPRING",
      "year": 1985,
      "month": "03"
    },
    "status": "FINISHED",
    "episodes": 1,
    "picture": "https://u.livechart.me/anime/7693/poster_image/3027f113c91e3fed12e0a66eeeffdf49.webp/large.jpg",
    "thumbnail": "https://u.livechart.me/anime/7693/poster_image/3027f113c91e3fed12e0a66eeeffdf49.webp/small.jpg",
    "synonyms": [
      "Doraemon Movie 6",
      "Doraemon Movie 6: Nobita no Little Star Wars",
      "Doraemon Movie 6: Nobita's Little Star Wars",
      "Doraemon Película 6: Doraemon y la Guerra de las Galaxias",
      "Doraemon the Movie: Nobita's Little Space War",
      "Doraemon: Nobita no Little Star Wars",
      "Doraemon: Nobita no Uchukosenso",
      "Doraemon: Nobita no Uchuu Shou Sensou",
      "Doraemon: Nobita's Little Star Wars",
      "Doraemon: Nobita`s Little Space War",
      "Doraemon: Nobita`s Little Star Wars",
      "Doraemon: Nobita’s Little Space War",
      "Doraemon: Nobita’s Little Star Wars",
      "Eiga Doraemon: Nobita no Little Star Wars",
      "ドラえもん のび太の宇宙小戦争",
      "ドラえもん のび太の宇宙小戦争[リトル・スター・ウォーズ]",
      "ドラえもん のび太の宇宙小戦争（リトル・スターウォーズ）",
      "哆啦A梦 大雄的宇宙小战争",
      "映画 ドラえもん のび太の宇宙小戦争[リトル・スター・ウォーズ]",
      "映画ドラえもん のび太の宇宙小戦争[リトル・スター・ウォーズ]"
    ]
  },
  {
    "title": "メガゾーン23",
    "titleTranslate": {
      "zh-Hans": [
        "无限地带23"
      ]
    },
    "type": "ova",
    "lang": "ja",
    "officialSite": "",
    "begin": "1985-03-09T16:00:00.000Z",
    "end": "1985-03-09T16:30:00.000Z",
    "sites": [
      {
        "site": "bangumi",
        "id": "33219"
      },
      {
        "site": "unext",
        "id": "SID0004894",
        "begin": "2015-06-01T06:00:00.000Z",
        "broadcast": "R/2015-06-01T06:00:00.000Z/P7D"
      }
    ],
    "animeSeason": {
      "season": "SPRING",
      "year": 1985,
      "month": "03"
    },
    "status": "FINISHED",
    "episodes": 4,
    "picture": "https://u.livechart.me/anime/6286/poster_image/0da9c443507c3ffb5d36729ac280e5b8.png/large.jpg",
    "thumbnail": "https://u.livechart.me/anime/6286/poster_image/0da9c443507c3ffb5d36729ac280e5b8.png/small.jpg",
    "synonyms": [
      "Megazone 23 Part II",
      "Megazone 23 Part III",
      "Robotech: The Untold Story (U.S.)",
      "めがぞーんつーすりー",
      "メガゾーン23"
    ]
  },
  {
    "title": "キン肉マン 正義超人VS古代超人",
    "titleTranslate": {
      "zh-Hans": [
        "筋肉人 正义超人vs古代超人"
      ]
    },
    "type": "movie",
    "lang": "ja",
    "officialSite": "",
    "begin": "1985-03-15T16:00:00.000Z",
    "broadcast": "",
    "end": "1985-03-15T16:00:00.000Z",
    "comment": "",
    "sites": [
      {
        "site": "bangumi",
        "id": "215102"
      },
      {
        "site": "unext",
        "id": "SID0003122",
        "begin": "2015-02-16T15:00:00.000Z",
        "broadcast": "R/2015-02-16T15:00:00.000Z/P7D"
      }
    ],
    "animeSeason": {
      "season": "SPRING",
      "year": 1985,
      "month": "03"
    },
    "status": "FINISHED",
    "episodes": 1,
    "picture": "https://u.livechart.me/anime/11866/poster_image/ad45cd1f519bba2d1088e9b3b75ba580.webp/large.jpg",
    "thumbnail": "https://u.livechart.me/anime/11866/poster_image/ad45cd1f519bba2d1088e9b3b75ba580.webp/small.jpg",
    "synonyms": [
      "Kinnikuman Movie 3: Seigi Choujin vs. Kodai Choujin",
      "Kinnikuman: Justice Superman Vs. Ancient Superman",
      "Kinnikuman: Justice Superman vs. Ancient Superman",
      "Kinnikuman: Seigi Choujin vs Kodai Choujin",
      "Kinnikuman: Seigi Chōjin vs Kodai Chōjin",
      "キン肉マン 正義超人VS古代超人",
      "キン肉マン 正義超人vs古代超人",
      "キン肉マン 正義超人ＶＳ古代超人",
      "筋肉人 正义超人vs古代超人"
    ]
  },
  {
    "title": "プロゴルファー猿",
    "titleTranslate": {
      "zh-Hans": [
        "球场小神将"
      ]
    },
    "type": "tv",
    "lang": "ja",
    "officialSite": "",
    "begin": "1982-10-18T16:00:00.000Z",
    "broadcast": "",
    "end": "1982-10-18T16:00:00.000Z",
    "comment": "",
    "sites": [
      {
        "site": "bangumi",
        "id": "189443"
      },
      {
        "site": "unext",
        "id": "SID0004906",
        "begin": "2016-02-18T15:00:00.000Z",
        "broadcast": "R/2016-02-18T15:00:00.000Z/P7D"
      }
    ],
    "animeSeason": {
      "season": "SPRING",
      "year": 1985,
      "month": "10"
    },
    "status": "FINISHED",
    "episodes": 143,
    "picture": "https://u.livechart.me/anime/12213/poster_image/5dad8f05729c28c8e58ba678bfafd25b.webp/large.jpg",
    "thumbnail": "https://u.livechart.me/anime/12213/poster_image/5dad8f05729c28c8e58ba678bfafd25b.webp/small.jpg",
    "synonyms": [
      "Pro Golfer Saru (1985)",
      "Pro Golfer Saru TV",
      "pgs",
      "プロゴルファー猿",
      "プロゴルファー猿 (1985)",
      "プロゴルファー猿 （1985）",
      "球场小神将（1985）"
    ]
  }
]