[
  {
    "title": "さよなら銀河鉄道999 -アンドロメダ終着駅-",
    "titleTranslate": {
      "zh-Hans": [
        "再见 银河铁道999 安卓梅达终点站"
      ]
    },
    "type": "movie",
    "lang": "ja",
    "officialSite": "",
    "begin": "1981-08-01T16:00:00.000Z",
    "end": "1981-08-01T18:15:00.000Z",
    "sites": [
      {
        "site": "bangumi",
        "id": "33922"
      },
      {
        "site": "anidb",
        "id": "2033"
      },
      {
        "site": "anidb",
        "id": "485"
      },
      {
        "site": "anilist",
        "id": "1000"
      },
      {
        "site": "anilist",
        "id": "1301"
      },
      {
        "site": "anilist",
        "id": "1553"
      },
      {
        "site": "anilist",
        "id": "3602"
      },
      {
        "site": "anime-planet",
        "id": "dna-sights-9999"
      },
      {
        "site": "anime-planet",
        "id": "galaxy-express-999"
      },
      {
        "site": "anime-planet",
        "id": "galaxy-express-999-can-you-live-like-a-warrior"
      },
      {
        "site": "anime-planet",
        "id": "galaxy-express-999-eternal-fantasy"
      },
      {
        "site": "anime-planet",
        "id": "galaxy-express-999-glass-no-clair"
      },
      {
        "site": "anime-planet",
        "id": "galaxy-express-999-movie"
      },
      {
        "site": "anime-planet",
        "id": "ginga-tetsudou-999-kimi-wa-haha-no-you-ni-aiseru-ka"
      },
      {
        "site": "anime-planet",
        "id": "maetel-legend"
      },
      {
        "site": "anime-planet",
        "id": "space-symphony-maetel-ginga-tetsudou-999-gaiden"
      },
      {
        "site": "anime-planet",
        "id": "the-galaxy-railways"
      },
      {
        "site": "anime-planet",
        "id": "the-galaxy-railways-a-letter-from-the-abandoned-planet"
      },
      {
        "site": "anime-planet",
        "id": "the-galaxy-railways-ii"
      },
      {
        "site": "anisearch",
        "id": "743"
      },
      {
        "site": "kitsu",
        "id": "1173"
      },
      {
        "site": "kitsu",
        "id": "3135"
      },
      {
        "site": "livechart",
        "id": "6299"
      },
      {
        "site": "livechart",
        "id": "7191"
      },
      {
        "site": "livechart",
        "id": "8401"
      },
      {
        "site": "livechart",
        "id": "8449"
      },
      {
        "site": "livechart",
        "id": "8596"
      },
      {
        "site": "livechart",
        "id": "8985"
      },
      {
        "site": "myanimelist",
        "id": "1301"
      },
      {
        "site": "myanimelist",
        "id": "3602"
      },
      {
        "site": "notify",
        "id": "Baml5FmmR"
      },
      {
        "site": "notify",
        "id": "ZgyxcFiig"
      }
    ],
    "animeSeason": {
      "season": "WINTER",
      "year": 1981,
      "month": "08"
    },
    "status": "FINISHED",
    "episodes": 1,
    "picture": "https://cdn.myanimelist.net/images/anime/1774/93957.jpg",
    "thumbnail": "https://cdn.myanimelist.net/images/anime/1774/93957t.jpg",
    "synonyms": [
      "Addio Galaxy Express 999 - Capolinea Andromeda",
      "Addio Galaxy Express 999: Capolinea Andromeda",
      "Adeus 999",
      "Adeus Expresso da Galáxia 999",
      "Adieu",
      "Adieu 999",
      "Adieu Galaxy Express 999",
      "Galaxy Express 999 - Capolinea Andromeda",
      "Galaxy Express 999: Last Stop Andromeda",
      "Goodbye 999",
      "Goodbye Galaxy Express 999: Andromeda Terminal Station",
      "Goodbye Galaxy Railway 999: Andromeda Terminal",
      "Sayonara 999",
      "Sayonara Galaxy Express 999",
      "Sayonara Ginga Tetsudo 999: Andromeda Shuuchakueki",
      "Sayonara Ginga Tetsudō 999: Andromeda Shūchakueki",
      "Sayonara, Galaxy Express 999",
      "ddio Galaxy Express 999 - Capolinea Andromeda",
      "Прощай, галактический экспресс 999: Терминал Андромеды",
      "さよなら銀河鉄道999 -アンドロメダ終着駅-",
      "再见 银河铁道999 安卓梅达终点站",
      "안녕",
      "은하철도 999"
    ]
  },
  {
    "title": "ドラえもん のび太の宇宙開拓史",
    "titleTranslate": {
      "zh-Hans": [
        "哆啦A梦：大雄的宇宙开拓史"
      ]
    },
    "type": "movie",
    "lang": "ja",
    "officialSite": "",
    "begin": "1981-03-16T16:00:00.000Z",
    "end": "1981-03-16T17:30:00.000Z",
    "sites": [
      {
        "site": "letv",
        "id": "80790",
        "begin": ""
      },
      {
        "site": "bangumi",
        "id": "436"
      },
      {
        "site": "qq",
        "id": "z/z8alyhrvkd3jp2y",
        "begin": ""
      },
      {
        "site": "bilibili",
        "id": "2550",
        "begin": "1981-03-13T16:00:00.000Z",
        "broadcast": "R/2015-02-13T08:01:00.000Z/P7D"
      },
      {
        "site": "abema",
        "id": "35-46",
        "begin": "",
        "broadcast": ""
      },
      {
        "site": "anidb",
        "id": "1078"
      },
      {
        "site": "anidb",
        "id": "6383"
      },
      {
        "site": "anilist",
        "id": "2471"
      },
      {
        "site": "anilist",
        "id": "6930"
      },
      {
        "site": "anime-planet",
        "id": "doraemon-1979"
      },
      {
        "site": "anime-planet",
        "id": "doraemon-doraemon-comes-back"
      },
      {
        "site": "anime-planet",
        "id": "doraemon-doraemon-comes-back-1998"
      },
      {
        "site": "anime-planet",
        "id": "doraemon-movie-29-shin-nobita-no-uchuu-kaitakushi"
      },
      {
        "site": "anime-planet",
        "id": "doraemon-nobita-no-shin-kyouryuu"
      },
      {
        "site": "anime-planet",
        "id": "the-doraemons-strange-sweets-strange"
      },
      {
        "site": "anisearch",
        "id": "4996"
      },
      {
        "site": "anisearch",
        "id": "540"
      },
      {
        "site": "kitsu",
        "id": "460"
      },
      {
        "site": "kitsu",
        "id": "4790"
      },
      {
        "site": "livechart",
        "id": "12164"
      },
      {
        "site": "livechart",
        "id": "5614"
      },
      {
        "site": "livechart",
        "id": "6575"
      },
      {
        "site": "livechart",
        "id": "6880"
      },
      {
        "site": "livechart",
        "id": "7693"
      },
      {
        "site": "livechart",
        "id": "8740"
      },
      {
        "site": "livechart",
        "id": "8868"
      },
      {
        "site": "livechart",
        "id": "8871"
      },
      {
        "site": "livechart",
        "id": "8877"
      },
      {
        "site": "livechart",
        "id": "8878"
      },
      {
        "site": "livechart",
        "id": "8884"
      },
      {
        "site": "livechart",
        "id": "8900"
      },
      {
        "site": "livechart",
        "id": "8901"
      },
      {
        "site": "livechart",
        "id": "8902"
      },
      {
        "site": "livechart",
        "id": "8998"
      },
      {
        "site": "myanimelist",
        "id": "2471"
      },
      {
        "site": "myanimelist",
        "id": "6930"
      },
      {
        "site": "notify",
        "id": "BRto5KimR"
      },
      {
        "site": "notify",
        "id": "nrGRpKmiR"
      }
    ],
    "animeSeason": {
      "season": "WINTER",
      "year": 1981,
      "month": "03"
    },
    "status": "FINISHED",
    "episodes": 1,
    "picture": "https://cdn.myanimelist.net/images/anime/8/72406.jpg",
    "thumbnail": "https://cdn.myanimelist.net/images/anime/8/72406t.jpg",
    "synonyms": [
      "Doraemon Movie 2",
      "Doraemon Movie 2: Nobita no Uchuu Kaitakushi",
      "Doraemon Película 2: Doraemon The Space Hero",
      "Doraemon The Space Hero",
      "Doraemon esplora lo spazio",
      "Doraemon the Movie: The Records of Nobita",
      "Doraemon the Movie: The Records of Nobita, Spaceblazer",
      "Doraemon: Nobita No Uchukaitakush",
      "Doraemon: Nobita no Uchuu Kaitakushi",
      "Doraemon: Nobita no Uchū Kaitakushi",
      "Doraemon: Nobita's Space Story",
      "Doraemon: The Records of Nobita",
      "Doraemon: The Records of Nobita, Spaceblazer",
      "Doraemon: The Space Hero",
      "Nobita the Space Colonist",
      "Nobita's How the Space Was Won",
      "Spaceblazer",
      "のび太の宇宙開拓史",
      "ドラえもん のび太の宇宙開拓史",
      "映画 ドラえもん のび太の宇宙開拓史"
    ]
  },
  {
    "title": "ユニコ",
    "titleTranslate": {
      "zh-Hans": [
        "小白角"
      ]
    },
    "type": "movie",
    "lang": "ja",
    "officialSite": "http://www.tms-e.com/library/old/tv/data/t_spank.html",
    "begin": "1981-03-12T16:00:00.000Z",
    "end": "1981-03-12T16:00:00.000Z",
    "sites": [
      {
        "site": "bangumi",
        "id": "32489"
      },
      {
        "site": "bilibili",
        "id": "5598",
        "begin": "2016-10-17T05:30:33.000Z",
        "broadcast": "R/2016-10-17T05:30:33.000Z/P7D"
      },
      {
        "site": "anidb",
        "id": "1361"
      },
      {
        "site": "anidb",
        "id": "1379"
      },
      {
        "site": "anidb",
        "id": "6396"
      },
      {
        "site": "anidb",
        "id": "7876"
      },
      {
        "site": "anidb",
        "id": "8488"
      },
      {
        "site": "anidb",
        "id": "9448"
      },
      {
        "site": "anilist",
        "id": "2213"
      },
      {
        "site": "anilist",
        "id": "2428"
      },
      {
        "site": "anilist",
        "id": "2429"
      },
      {
        "site": "anime-planet",
        "id": "saving-our-fragile-earth-unico-special-chapter"
      },
      {
        "site": "anime-planet",
        "id": "unico-in-the-island-of-magic"
      },
      {
        "site": "anime-planet",
        "id": "unico-kuroi-kumo-to-shiroi-hane"
      },
      {
        "site": "anisearch",
        "id": "3403"
      },
      {
        "site": "anisearch",
        "id": "7171"
      },
      {
        "site": "anisearch",
        "id": "779"
      },
      {
        "site": "anisearch",
        "id": "8116"
      },
      {
        "site": "kitsu",
        "id": "2202"
      },
      {
        "site": "kitsu",
        "id": "2203"
      },
      {
        "site": "kitsu",
        "id": "8988"
      },
      {
        "site": "livechart",
        "id": "6924"
      },
      {
        "site": "livechart",
        "id": "8137"
      },
      {
        "site": "myanimelist",
        "id": "23661"
      },
      {
        "site": "myanimelist",
        "id": "2428"
      },
      {
        "site": "myanimelist",
        "id": "2429"
      },
      {
        "site": "notify",
        "id": "DjUE5KmiR"
      },
      {
        "site": "notify",
        "id": "VzwPcFiig"
      },
      {
        "site": "notify",
        "id": "Z1wxpFmmR"
      }
    ],
    "animeSeason": {
      "season": "WINTER",
      "year": 1981,
      "month": "03"
    },
    "status": "FINISHED",
    "episodes": 1,
    "picture": "https://cdn.myanimelist.net/images/anime/1601/112164.jpg",
    "thumbnail": "https://cdn.myanimelist.net/images/anime/1601/112164t.jpg",
    "synonyms": [
      "A kis egyszarvú",
      "Fantastic Adventures of Unico",
      "Le fantastiche avventure di Unico",
      "The Fantastic Adventures Of Unico",
      "The Fantastic Adventures of Unico",
      "The Fantastic Adventures of Unico 1",
      "Unico - Das Hörnchen",
      "Unico Movie 1",
      "Unico il piccolo unicorno",
      "Unico. El Pequeño Unicornio",
      "Unico: Das phantastische Abenteuer eines Hörnchens",
      "Unico: El Pequeño Unicornio",
      "Юнико",
      "ユニコ",
      "小白角"
    ]
  },
  {
    "title": "家族ロビンソン漂流記ふしぎな島のフローネ",
    "titleTranslate": {
      "zh-Hans": [
        "鲁滨逊一家漂流记",
        "新鲁宾逊漂流记"
      ]
    },
    "type": "tv",
    "lang": "ja",
    "officialSite": "http://www.nippon-animation.co.jp/work/fushiginashimano_flone.html",
    "begin": "1981-01-04T22:30:00.000Z",
    "end": "1981-12-27T23:00:00.000Z",
    "sites": [
      {
        "site": "iqiyi",
        "id": "a_19rrjzgszx",
        "begin": "2012-10-16T10:38:34.000Z"
      },
      {
        "site": "bangumi",
        "id": "23612"
      },
      {
        "site": "anidb",
        "id": "7144"
      },
      {
        "site": "anime-planet",
        "id": "kazoku-robinson-hyouryuuki-fushigi-na-shima-no-flone-specials"
      },
      {
        "site": "anisearch",
        "id": "6133"
      },
      {
        "site": "kitsu",
        "id": "9373"
      },
      {
        "site": "myanimelist",
        "id": "24681"
      },
      {
        "site": "notify",
        "id": "8XHftFiiR"
      }
    ],
    "animeSeason": {
      "season": "WINTER",
      "year": 1981,
      "month": "01"
    },
    "status": "FINISHED",
    "episodes": 50,
    "picture": "https://cdn.myanimelist.net/images/anime/1191/98626.jpg",
    "thumbnail": "https://cdn.myanimelist.net/images/anime/1191/98626t.jpg",
    "synonyms": [
      "A Familia Robinson",
      "A Família Robinson",
      "De Familie Robinson",
      "Die schweizer Familie Robinson",
      "Familie Robinson",
      "Flo et les Robinson Suisses",
      "Flo et les Robinson suisses",
      "Flo, la piccola Robinson",
      "Fushigi na Shima no Flone",
      "Kazoku Robinson Hyouryuuki: Fushigima Shima no Flone",
      "Kazoku Robinson Hyōryūki: Fushigi na Shima no Flone",
      "L' Isola Della Piccola Flo",
      "La Familia Robinson",
      "La familia Robinson",
      "Robinson Family Lost at Sea: Flone of the Marvelous Island",
      "Sekai Meisaku Gekijou",
      "Swiss Family Robinson",
      "Swiss Family Robinson (TV)",
      "The Swiss Family Robinson",
      "The Swiss Family Robinson: Flone of the Mysterious Island",
      "WMT",
      "World Masterpiece Theater",
      "Флона на чудесном острове",
      "خانواده دکتر اِرنِست",
      "عائلة روبنسون السويسرية",
      "فلونة",
      "家族ロビンソン漂流記 ふしぎな島のフローネ",
      "家族ロビンソン漂流記ふしぎな島のフローネ"
    ]
  },
  {
    "title": "最強ロボ ダイオージャ",
    "titleTranslate": {
      "zh-Hans": [
        "最强机器人 大王者"
      ]
    },
    "type": "tv",
    "lang": "ja",
    "officialSite": "",
    "begin": "1981-01-30T16:00:00.000Z",
    "end": "1982-01-29T16:00:00.000Z",
    "sites": [
      {
        "site": "bangumi",
        "id": "37287"
      },
      {
        "site": "bilibili",
        "id": "3134",
        "begin": "2015-12-05T01:42:48.000Z",
        "broadcast": "R/2015-12-05T01:42:48.000Z/P7D"
      }
    ],
    "animeSeason": {
      "season": "WINTER",
      "year": 1981,
      "month": "01"
    },
    "status": "FINISHED",
    "episodes": 50,
    "picture": "https://cdn.myanimelist.net/images/anime/1170/93954.jpg",
    "thumbnail": "https://cdn.myanimelist.net/images/anime/1170/93954t.jpg",
    "synonyms": [
      "Robot King Daioja",
      "Saikyou Robo Daiohja",
      "Saikyou Robo Daioja",
      "Saikyou Robo Daiouja",
      "Saikyou Robot Daioja",
      "Saikyō Robo Daiōja",
      "Ultimate Robo Daihoja",
      "Ultimate Robo Daiohja",
      "最強ロボ ダイオージャ"
    ]
  }
]